{
  "system-security-plan": {
    "uuid": "73759548-64c2-4ca3-8ffc-fd2d186f892c",
    "metadata": {
      "title": "Ubuntu System Security Plan - FedRAMP Moderate",
      "last-modified": "2026-05-08T16:02:57.080008",
      "version": "1.0",
      "oscal-version": "1.2.1"
    },
    "import-profile": {
      "href": "trestle://profiles/FedRAMP-Rev5-Moderate/profile.json"
    },
    "system-characteristics": {
      "system-ids": [
        {
          "id": "ubuntu-system-001"
        }
      ],
      "system-name": "Ubuntu 24.04 LTS Fleet",
      "description": "System Security Plan for Ubuntu Linux 24.04 LTS 6-server fleet with OSCAP compliance validation - FedRAMP Moderate baseline",
      "security-sensitivity-level": "moderate",
      "system-information": {
        "information-types": [
          {
            "title": "System and Network Configuration",
            "description": "Information related to system configuration, security settings, compliance validation, and network infrastructure"
          }
        ]
      },
      "status": {
        "state": "operational"
      },
      "authorization-boundary": {
        "description": "Ubuntu Linux 24.04 LTS 6-server fleet operating within a single authorization boundary, implementing FedRAMP Moderate security controls"
      }
    },
    "system-implementation": {
      "users": [
        {
          "uuid": "f0a038dc-bf0f-44f7-b1fb-4accbf369ca3",
          "title": "System Administrator",
          "role-ids": [
            "admin"
          ]
        }
      ],
      "components": [
        {
          "uuid": "b2e11579-d4d6-48f8-a43c-ec7157543648",
          "type": "software",
          "title": "Ubuntu_Linux_24.04_LTS",
          "description": "Ubuntu Linux 24.04 LTS",
          "props": [
            {
              "name": "Rule_Id",
              "ns": "https://oscal-compass/compliance-trestle/schemas/oscal/cd",
              "value": "accounts_password_pam_unix_enabled",
              "remarks": "rule_set_00"
            },
            {
              "name": "Rule_Description",
              "ns": "https://oscal-compass/compliance-trestle/schemas/oscal/cd",
              "value": "accounts_password_pam_unix_enabled",
              "remarks": "rule_set_00"
            },
            {
              "name": "Rule_Id",
              "ns": "https://oscal-compass/compliance-trestle/schemas/oscal/cd",
              "value": "accounts_root_gid_zero",
              "remarks": "rule_set_01"
            },
            {
              "name": "Rule_Description",
              "ns": "https://oscal-compass/compliance-trestle/schemas/oscal/cd",
              "value": "accounts_root_gid_zero",
              "remarks": "rule_set_01"
            },
            {
              "name": "Rule_Id",
              "ns": "https://oscal-compass/compliance-trestle/schemas/oscal/cd",
              "value": "accounts_umask_etc_bashrc",
              "remarks": "rule_set_02"
            },
            {
              "name": "Rule_Description",
              "ns": "https://oscal-compass/compliance-trestle/schemas/oscal/cd",
              "value": "accounts_umask_etc_bashrc",
              "remarks": "rule_set_02"
            },
            {
              "name": "Rule_Id",
              "ns": "https://oscal-compass/compliance-trestle/schemas/oscal/cd",
              "value": "accounts_umask_etc_login_defs",
              "remarks": "rule_set_03"
            },
            {
              "name": "Rule_Description",
              "ns": "https://oscal-compass/compliance-trestle/schemas/oscal/cd",
              "value": "accounts_umask_etc_login_defs",
              "remarks": "rule_set_03"
            },
            {
              "name": "Rule_Id",
              "ns": "https://oscal-compass/compliance-trestle/schemas/oscal/cd",
              "value": "accounts_umask_etc_profile",
              "remarks": "rule_set_04"
            },
            {
              "name": "Rule_Description",
              "ns": "https://oscal-compass/compliance-trestle/schemas/oscal/cd",
              "value": "accounts_umask_etc_profile",
              "remarks": "rule_set_04"
            },
            {
              "name": "Rule_Id",
              "ns": "https://oscal-compass/compliance-trestle/schemas/oscal/cd",
              "value": "accounts_umask_root",
              "remarks": "rule_set_05"
            },
            {
              "name": "Rule_Description",
              "ns": "https://oscal-compass/compliance-trestle/schemas/oscal/cd",
              "value": "accounts_umask_root",
              "remarks": "rule_set_05"
            },
            {
              "name": "Rule_Id",
              "ns": "https://oscal-compass/compliance-trestle/schemas/oscal/cd",
              "value": "ensure_pam_wheel_group_empty",
              "remarks": "rule_set_06"
            },
            {
              "name": "Rule_Description",
              "ns": "https://oscal-compass/compliance-trestle/schemas/oscal/cd",
              "value": "ensure_pam_wheel_group_empty",
              "remarks": "rule_set_06"
            },
            {
              "name": "Rule_Id",
              "ns": "https://oscal-compass/compliance-trestle/schemas/oscal/cd",
              "value": "ensure_root_access_controlled",
              "remarks": "rule_set_07"
            },
            {
              "name": "Rule_Description",
              "ns": "https://oscal-compass/compliance-trestle/schemas/oscal/cd",
              "value": "ensure_root_access_controlled",
              "remarks": "rule_set_07"
            },
            {
              "name": "Rule_Id",
              "ns": "https://oscal-compass/compliance-trestle/schemas/oscal/cd",
              "value": "file_groupowner_sshd_config",
              "remarks": "rule_set_08"
            },
            {
              "name": "Rule_Description",
              "ns": "https://oscal-compass/compliance-trestle/schemas/oscal/cd",
              "value": "file_groupowner_sshd_config",
              "remarks": "rule_set_08"
            },
            {
              "name": "Rule_Id",
              "ns": "https://oscal-compass/compliance-trestle/schemas/oscal/cd",
              "value": "file_owner_sshd_config",
              "remarks": "rule_set_09"
            },
            {
              "name": "Rule_Description",
              "ns": "https://oscal-compass/compliance-trestle/schemas/oscal/cd",
              "value": "file_owner_sshd_config",
              "remarks": "rule_set_09"
            },
            {
              "name": "Rule_Id",
              "ns": "https://oscal-compass/compliance-trestle/schemas/oscal/cd",
              "value": "file_permissions_sshd_config",
              "remarks": "rule_set_10"
            },
            {
              "name": "Rule_Description",
              "ns": "https://oscal-compass/compliance-trestle/schemas/oscal/cd",
              "value": "file_permissions_sshd_config",
              "remarks": "rule_set_10"
            },
            {
              "name": "Rule_Id",
              "ns": "https://oscal-compass/compliance-trestle/schemas/oscal/cd",
              "value": "file_permissions_sshd_private_key",
              "remarks": "rule_set_11"
            },
            {
              "name": "Rule_Description",
              "ns": "https://oscal-compass/compliance-trestle/schemas/oscal/cd",
              "value": "file_permissions_sshd_private_key",
              "remarks": "rule_set_11"
            },
            {
              "name": "Rule_Id",
              "ns": "https://oscal-compass/compliance-trestle/schemas/oscal/cd",
              "value": "file_permissions_sshd_pub_key",
              "remarks": "rule_set_12"
            },
            {
              "name": "Rule_Description",
              "ns": "https://oscal-compass/compliance-trestle/schemas/oscal/cd",
              "value": "file_permissions_sshd_pub_key",
              "remarks": "rule_set_12"
            },
            {
              "name": "Rule_Id",
              "ns": "https://oscal-compass/compliance-trestle/schemas/oscal/cd",
              "value": "groups_no_zero_gid_except_root",
              "remarks": "rule_set_13"
            },
            {
              "name": "Rule_Description",
              "ns": "https://oscal-compass/compliance-trestle/schemas/oscal/cd",
              "value": "groups_no_zero_gid_except_root",
              "remarks": "rule_set_13"
            },
            {
              "name": "Rule_Id",
              "ns": "https://oscal-compass/compliance-trestle/schemas/oscal/cd",
              "value": "no_invalid_shell_accounts_unlocked",
              "remarks": "rule_set_14"
            },
            {
              "name": "Rule_Description",
              "ns": "https://oscal-compass/compliance-trestle/schemas/oscal/cd",
              "value": "no_invalid_shell_accounts_unlocked",
              "remarks": "rule_set_14"
            },
            {
              "name": "Rule_Id",
              "ns": "https://oscal-compass/compliance-trestle/schemas/oscal/cd",
              "value": "no_shelllogin_for_systemaccounts",
              "remarks": "rule_set_15"
            },
            {
              "name": "Rule_Description",
              "ns": "https://oscal-compass/compliance-trestle/schemas/oscal/cd",
              "value": "no_shelllogin_for_systemaccounts",
              "remarks": "rule_set_15"
            },
            {
              "name": "Rule_Id",
              "ns": "https://oscal-compass/compliance-trestle/schemas/oscal/cd",
              "value": "sshd_limit_user_access",
              "remarks": "rule_set_16"
            },
            {
              "name": "Rule_Description",
              "ns": "https://oscal-compass/compliance-trestle/schemas/oscal/cd",
              "value": "sshd_limit_user_access",
              "remarks": "rule_set_16"
            },
            {
              "name": "Rule_Id",
              "ns": "https://oscal-compass/compliance-trestle/schemas/oscal/cd",
              "value": "use_pam_wheel_group_for_su",
              "remarks": "rule_set_17"
            },
            {
              "name": "Rule_Description",
              "ns": "https://oscal-compass/compliance-trestle/schemas/oscal/cd",
              "value": "use_pam_wheel_group_for_su",
              "remarks": "rule_set_17"
            },
            {
              "name": "Rule_Id",
              "ns": "https://oscal-compass/compliance-trestle/schemas/oscal/cd",
              "value": "sshd_use_strong_ciphers",
              "remarks": "rule_set_18"
            },
            {
              "name": "Rule_Description",
              "ns": "https://oscal-compass/compliance-trestle/schemas/oscal/cd",
              "value": "sshd_use_strong_ciphers",
              "remarks": "rule_set_18"
            },
            {
              "name": "Rule_Id",
              "ns": "https://oscal-compass/compliance-trestle/schemas/oscal/cd",
              "value": "sshd_use_strong_kex",
              "remarks": "rule_set_19"
            },
            {
              "name": "Rule_Description",
              "ns": "https://oscal-compass/compliance-trestle/schemas/oscal/cd",
              "value": "sshd_use_strong_kex",
              "remarks": "rule_set_19"
            },
            {
              "name": "Rule_Id",
              "ns": "https://oscal-compass/compliance-trestle/schemas/oscal/cd",
              "value": "sshd_use_strong_macs",
              "remarks": "rule_set_20"
            },
            {
              "name": "Rule_Description",
              "ns": "https://oscal-compass/compliance-trestle/schemas/oscal/cd",
              "value": "sshd_use_strong_macs",
              "remarks": "rule_set_20"
            },
            {
              "name": "Rule_Id",
              "ns": "https://oscal-compass/compliance-trestle/schemas/oscal/cd",
              "value": "accounts_password_pam_pwhistory_use_authtok",
              "remarks": "rule_set_21"
            },
            {
              "name": "Rule_Description",
              "ns": "https://oscal-compass/compliance-trestle/schemas/oscal/cd",
              "value": "accounts_password_pam_pwhistory_use_authtok",
              "remarks": "rule_set_21"
            },
            {
              "name": "Rule_Id",
              "ns": "https://oscal-compass/compliance-trestle/schemas/oscal/cd",
              "value": "accounts_password_pam_unix_authtok",
              "remarks": "rule_set_22"
            },
            {
              "name": "Rule_Description",
              "ns": "https://oscal-compass/compliance-trestle/schemas/oscal/cd",
              "value": "accounts_password_pam_unix_authtok",
              "remarks": "rule_set_22"
            },
            {
              "name": "Rule_Id",
              "ns": "https://oscal-compass/compliance-trestle/schemas/oscal/cd",
              "value": "set_password_hashing_algorithm_logindefs",
              "remarks": "rule_set_23"
            },
            {
              "name": "Rule_Description",
              "ns": "https://oscal-compass/compliance-trestle/schemas/oscal/cd",
              "value": "set_password_hashing_algorithm_logindefs",
              "remarks": "rule_set_23"
            },
            {
              "name": "Rule_Id",
              "ns": "https://oscal-compass/compliance-trestle/schemas/oscal/cd",
              "value": "set_password_hashing_algorithm_systemauth",
              "remarks": "rule_set_24"
            },
            {
              "name": "Rule_Description",
              "ns": "https://oscal-compass/compliance-trestle/schemas/oscal/cd",
              "value": "set_password_hashing_algorithm_systemauth",
              "remarks": "rule_set_24"
            },
            {
              "name": "Rule_Id",
              "ns": "https://oscal-compass/compliance-trestle/schemas/oscal/cd",
              "value": "account_disable_post_pw_expiration",
              "remarks": "rule_set_25"
            },
            {
              "name": "Rule_Description",
              "ns": "https://oscal-compass/compliance-trestle/schemas/oscal/cd",
              "value": "account_disable_post_pw_expiration",
              "remarks": "rule_set_25"
            },
            {
              "name": "Rule_Id",
              "ns": "https://oscal-compass/compliance-trestle/schemas/oscal/cd",
              "value": "accounts_maximum_age_login_defs",
              "remarks": "rule_set_26"
            },
            {
              "name": "Rule_Description",
              "ns": "https://oscal-compass/compliance-trestle/schemas/oscal/cd",
              "value": "accounts_maximum_age_login_defs",
              "remarks": "rule_set_26"
            },
            {
              "name": "Rule_Id",
              "ns": "https://oscal-compass/compliance-trestle/schemas/oscal/cd",
              "value": "accounts_minimum_age_login_defs",
              "remarks": "rule_set_27"
            },
            {
              "name": "Rule_Description",
              "ns": "https://oscal-compass/compliance-trestle/schemas/oscal/cd",
              "value": "accounts_minimum_age_login_defs",
              "remarks": "rule_set_27"
            },
            {
              "name": "Rule_Id",
              "ns": "https://oscal-compass/compliance-trestle/schemas/oscal/cd",
              "value": "accounts_password_last_change_is_in_past",
              "remarks": "rule_set_28"
            },
            {
              "name": "Rule_Description",
              "ns": "https://oscal-compass/compliance-trestle/schemas/oscal/cd",
              "value": "accounts_password_last_change_is_in_past",
              "remarks": "rule_set_28"
            },
            {
              "name": "Rule_Id",
              "ns": "https://oscal-compass/compliance-trestle/schemas/oscal/cd",
              "value": "accounts_password_pam_dcredit",
              "remarks": "rule_set_29"
            },
            {
              "name": "Rule_Description",
              "ns": "https://oscal-compass/compliance-trestle/schemas/oscal/cd",
              "value": "accounts_password_pam_dcredit",
              "remarks": "rule_set_29"
            },
            {
              "name": "Rule_Id",
              "ns": "https://oscal-compass/compliance-trestle/schemas/oscal/cd",
              "value": "accounts_password_pam_dictcheck",
              "remarks": "rule_set_30"
            },
            {
              "name": "Rule_Description",
              "ns": "https://oscal-compass/compliance-trestle/schemas/oscal/cd",
              "value": "accounts_password_pam_dictcheck",
              "remarks": "rule_set_30"
            },
            {
              "name": "Rule_Id",
              "ns": "https://oscal-compass/compliance-trestle/schemas/oscal/cd",
              "value": "accounts_password_pam_difok",
              "remarks": "rule_set_31"
            },
            {
              "name": "Rule_Description",
              "ns": "https://oscal-compass/compliance-trestle/schemas/oscal/cd",
              "value": "accounts_password_pam_difok",
              "remarks": "rule_set_31"
            },
            {
              "name": "Rule_Id",
              "ns": "https://oscal-compass/compliance-trestle/schemas/oscal/cd",
              "value": "accounts_password_pam_enforce_root",
              "remarks": "rule_set_32"
            },
            {
              "name": "Rule_Description",
              "ns": "https://oscal-compass/compliance-trestle/schemas/oscal/cd",
              "value": "accounts_password_pam_enforce_root",
              "remarks": "rule_set_32"
            },
            {
              "name": "Rule_Id",
              "ns": "https://oscal-compass/compliance-trestle/schemas/oscal/cd",
              "value": "accounts_password_pam_enforcing",
              "remarks": "rule_set_33"
            },
            {
              "name": "Rule_Description",
              "ns": "https://oscal-compass/compliance-trestle/schemas/oscal/cd",
              "value": "accounts_password_pam_enforcing",
              "remarks": "rule_set_33"
            },
            {
              "name": "Rule_Id",
              "ns": "https://oscal-compass/compliance-trestle/schemas/oscal/cd",
              "value": "accounts_password_pam_lcredit",
              "remarks": "rule_set_34"
            },
            {
              "name": "Rule_Description",
              "ns": "https://oscal-compass/compliance-trestle/schemas/oscal/cd",
              "value": "accounts_password_pam_lcredit",
              "remarks": "rule_set_34"
            },
            {
              "name": "Rule_Id",
              "ns": "https://oscal-compass/compliance-trestle/schemas/oscal/cd",
              "value": "accounts_password_pam_maxrepeat",
              "remarks": "rule_set_35"
            },
            {
              "name": "Rule_Description",
              "ns": "https://oscal-compass/compliance-trestle/schemas/oscal/cd",
              "value": "accounts_password_pam_maxrepeat",
              "remarks": "rule_set_35"
            },
            {
              "name": "Rule_Id",
              "ns": "https://oscal-compass/compliance-trestle/schemas/oscal/cd",
              "value": "accounts_password_pam_maxsequence",
              "remarks": "rule_set_36"
            },
            {
              "name": "Rule_Description",
              "ns": "https://oscal-compass/compliance-trestle/schemas/oscal/cd",
              "value": "accounts_password_pam_maxsequence",
              "remarks": "rule_set_36"
            },
            {
              "name": "Rule_Id",
              "ns": "https://oscal-compass/compliance-trestle/schemas/oscal/cd",
              "value": "accounts_password_pam_minclass",
              "remarks": "rule_set_37"
            },
            {
              "name": "Rule_Description",
              "ns": "https://oscal-compass/compliance-trestle/schemas/oscal/cd",
              "value": "accounts_password_pam_minclass",
              "remarks": "rule_set_37"
            },
            {
              "name": "Rule_Id",
              "ns": "https://oscal-compass/compliance-trestle/schemas/oscal/cd",
              "value": "accounts_password_pam_minlen",
              "remarks": "rule_set_38"
            },
            {
              "name": "Rule_Description",
              "ns": "https://oscal-compass/compliance-trestle/schemas/oscal/cd",
              "value": "accounts_password_pam_minlen",
              "remarks": "rule_set_38"
            },
            {
              "name": "Rule_Id",
              "ns": "https://oscal-compass/compliance-trestle/schemas/oscal/cd",
              "value": "accounts_password_pam_ocredit",
              "remarks": "rule_set_39"
            },
            {
              "name": "Rule_Description",
              "ns": "https://oscal-compass/compliance-trestle/schemas/oscal/cd",
              "value": "accounts_password_pam_ocredit",
              "remarks": "rule_set_39"
            },
            {
              "name": "Rule_Id",
              "ns": "https://oscal-compass/compliance-trestle/schemas/oscal/cd",
              "value": "accounts_password_pam_pwhistory_enabled",
              "remarks": "rule_set_40"
            },
            {
              "name": "Rule_Description",
              "ns": "https://oscal-compass/compliance-trestle/schemas/oscal/cd",
              "value": "accounts_password_pam_pwhistory_enabled",
              "remarks": "rule_set_40"
            },
            {
              "name": "Rule_Id",
              "ns": "https://oscal-compass/compliance-trestle/schemas/oscal/cd",
              "value": "accounts_password_pam_pwhistory_enforce_root",
              "remarks": "rule_set_41"
            },
            {
              "name": "Rule_Description",
              "ns": "https://oscal-compass/compliance-trestle/schemas/oscal/cd",
              "value": "accounts_password_pam_pwhistory_enforce_root",
              "remarks": "rule_set_41"
            },
            {
              "name": "Rule_Id",
              "ns": "https://oscal-compass/compliance-trestle/schemas/oscal/cd",
              "value": "accounts_password_pam_pwhistory_remember",
              "remarks": "rule_set_42"
            },
            {
              "name": "Rule_Description",
              "ns": "https://oscal-compass/compliance-trestle/schemas/oscal/cd",
              "value": "accounts_password_pam_pwhistory_remember",
              "remarks": "rule_set_42"
            },
            {
              "name": "Rule_Id",
              "ns": "https://oscal-compass/compliance-trestle/schemas/oscal/cd",
              "value": "accounts_password_pam_pwquality_enabled",
              "remarks": "rule_set_43"
            },
            {
              "name": "Rule_Description",
              "ns": "https://oscal-compass/compliance-trestle/schemas/oscal/cd",
              "value": "accounts_password_pam_pwquality_enabled",
              "remarks": "rule_set_43"
            },
            {
              "name": "Rule_Id",
              "ns": "https://oscal-compass/compliance-trestle/schemas/oscal/cd",
              "value": "accounts_password_pam_ucredit",
              "remarks": "rule_set_44"
            },
            {
              "name": "Rule_Description",
              "ns": "https://oscal-compass/compliance-trestle/schemas/oscal/cd",
              "value": "accounts_password_pam_ucredit",
              "remarks": "rule_set_44"
            },
            {
              "name": "Rule_Id",
              "ns": "https://oscal-compass/compliance-trestle/schemas/oscal/cd",
              "value": "accounts_password_pam_unix_no_remember",
              "remarks": "rule_set_45"
            },
            {
              "name": "Rule_Description",
              "ns": "https://oscal-compass/compliance-trestle/schemas/oscal/cd",
              "value": "accounts_password_pam_unix_no_remember",
              "remarks": "rule_set_45"
            },
            {
              "name": "Rule_Id",
              "ns": "https://oscal-compass/compliance-trestle/schemas/oscal/cd",
              "value": "accounts_password_set_max_life_existing",
              "remarks": "rule_set_46"
            },
            {
              "name": "Rule_Description",
              "ns": "https://oscal-compass/compliance-trestle/schemas/oscal/cd",
              "value": "accounts_password_set_max_life_existing",
              "remarks": "rule_set_46"
            },
            {
              "name": "Rule_Id",
              "ns": "https://oscal-compass/compliance-trestle/schemas/oscal/cd",
              "value": "accounts_password_set_min_life_existing",
              "remarks": "rule_set_47"
            },
            {
              "name": "Rule_Description",
              "ns": "https://oscal-compass/compliance-trestle/schemas/oscal/cd",
              "value": "accounts_password_set_min_life_existing",
              "remarks": "rule_set_47"
            },
            {
              "name": "Rule_Id",
              "ns": "https://oscal-compass/compliance-trestle/schemas/oscal/cd",
              "value": "no_empty_passwords_unix",
              "remarks": "rule_set_48"
            },
            {
              "name": "Rule_Description",
              "ns": "https://oscal-compass/compliance-trestle/schemas/oscal/cd",
              "value": "no_empty_passwords_unix",
              "remarks": "rule_set_48"
            },
            {
              "name": "Rule_Id",
              "ns": "https://oscal-compass/compliance-trestle/schemas/oscal/cd",
              "value": "sshd_disable_empty_passwords",
              "remarks": "rule_set_49"
            },
            {
              "name": "Rule_Description",
              "ns": "https://oscal-compass/compliance-trestle/schemas/oscal/cd",
              "value": "sshd_disable_empty_passwords",
              "remarks": "rule_set_49"
            },
            {
              "name": "Rule_Id",
              "ns": "https://oscal-compass/compliance-trestle/schemas/oscal/cd",
              "value": "sshd_disable_gssapi_auth",
              "remarks": "rule_set_50"
            },
            {
              "name": "Rule_Description",
              "ns": "https://oscal-compass/compliance-trestle/schemas/oscal/cd",
              "value": "sshd_disable_gssapi_auth",
              "remarks": "rule_set_50"
            },
            {
              "name": "Rule_Id",
              "ns": "https://oscal-compass/compliance-trestle/schemas/oscal/cd",
              "value": "sshd_disable_rhosts",
              "remarks": "rule_set_51"
            },
            {
              "name": "Rule_Description",
              "ns": "https://oscal-compass/compliance-trestle/schemas/oscal/cd",
              "value": "sshd_disable_rhosts",
              "remarks": "rule_set_51"
            },
            {
              "name": "Rule_Id",
              "ns": "https://oscal-compass/compliance-trestle/schemas/oscal/cd",
              "value": "sshd_enable_pam",
              "remarks": "rule_set_52"
            },
            {
              "name": "Rule_Description",
              "ns": "https://oscal-compass/compliance-trestle/schemas/oscal/cd",
              "value": "sshd_enable_pam",
              "remarks": "rule_set_52"
            },
            {
              "name": "Rule_Id",
              "ns": "https://oscal-compass/compliance-trestle/schemas/oscal/cd",
              "value": "accounts_password_warn_age_login_defs",
              "remarks": "rule_set_53"
            },
            {
              "name": "Rule_Description",
              "ns": "https://oscal-compass/compliance-trestle/schemas/oscal/cd",
              "value": "accounts_password_warn_age_login_defs",
              "remarks": "rule_set_53"
            },
            {
              "name": "Rule_Id",
              "ns": "https://oscal-compass/compliance-trestle/schemas/oscal/cd",
              "value": "sshd_disable_forwarding",
              "remarks": "rule_set_54"
            },
            {
              "name": "Rule_Description",
              "ns": "https://oscal-compass/compliance-trestle/schemas/oscal/cd",
              "value": "sshd_disable_forwarding",
              "remarks": "rule_set_54"
            },
            {
              "name": "Rule_Id",
              "ns": "https://oscal-compass/compliance-trestle/schemas/oscal/cd",
              "value": "accounts_tmout",
              "remarks": "rule_set_55"
            },
            {
              "name": "Rule_Description",
              "ns": "https://oscal-compass/compliance-trestle/schemas/oscal/cd",
              "value": "accounts_tmout",
              "remarks": "rule_set_55"
            },
            {
              "name": "Rule_Id",
              "ns": "https://oscal-compass/compliance-trestle/schemas/oscal/cd",
              "value": "package_sudo_installed",
              "remarks": "rule_set_56"
            },
            {
              "name": "Rule_Description",
              "ns": "https://oscal-compass/compliance-trestle/schemas/oscal/cd",
              "value": "package_sudo_installed",
              "remarks": "rule_set_56"
            },
            {
              "name": "Rule_Id",
              "ns": "https://oscal-compass/compliance-trestle/schemas/oscal/cd",
              "value": "sshd_disable_root_login",
              "remarks": "rule_set_57"
            },
            {
              "name": "Rule_Description",
              "ns": "https://oscal-compass/compliance-trestle/schemas/oscal/cd",
              "value": "sshd_disable_root_login",
              "remarks": "rule_set_57"
            },
            {
              "name": "Rule_Id",
              "ns": "https://oscal-compass/compliance-trestle/schemas/oscal/cd",
              "value": "sudo_add_use_pty",
              "remarks": "rule_set_58"
            },
            {
              "name": "Rule_Description",
              "ns": "https://oscal-compass/compliance-trestle/schemas/oscal/cd",
              "value": "sudo_add_use_pty",
              "remarks": "rule_set_58"
            },
            {
              "name": "Rule_Id",
              "ns": "https://oscal-compass/compliance-trestle/schemas/oscal/cd",
              "value": "sudo_remove_no_authenticate",
              "remarks": "rule_set_59"
            },
            {
              "name": "Rule_Description",
              "ns": "https://oscal-compass/compliance-trestle/schemas/oscal/cd",
              "value": "sudo_remove_no_authenticate",
              "remarks": "rule_set_59"
            },
            {
              "name": "Rule_Id",
              "ns": "https://oscal-compass/compliance-trestle/schemas/oscal/cd",
              "value": "sudo_require_authentication",
              "remarks": "rule_set_60"
            },
            {
              "name": "Rule_Description",
              "ns": "https://oscal-compass/compliance-trestle/schemas/oscal/cd",
              "value": "sudo_require_authentication",
              "remarks": "rule_set_60"
            },
            {
              "name": "Rule_Id",
              "ns": "https://oscal-compass/compliance-trestle/schemas/oscal/cd",
              "value": "sudo_require_reauthentication",
              "remarks": "rule_set_61"
            },
            {
              "name": "Rule_Description",
              "ns": "https://oscal-compass/compliance-trestle/schemas/oscal/cd",
              "value": "sudo_require_reauthentication",
              "remarks": "rule_set_61"
            },
            {
              "name": "Rule_Id",
              "ns": "https://oscal-compass/compliance-trestle/schemas/oscal/cd",
              "value": "accounts_passwords_pam_faillock_deny",
              "remarks": "rule_set_62"
            },
            {
              "name": "Rule_Description",
              "ns": "https://oscal-compass/compliance-trestle/schemas/oscal/cd",
              "value": "accounts_passwords_pam_faillock_deny",
              "remarks": "rule_set_62"
            },
            {
              "name": "Rule_Id",
              "ns": "https://oscal-compass/compliance-trestle/schemas/oscal/cd",
              "value": "accounts_passwords_pam_faillock_enabled",
              "remarks": "rule_set_63"
            },
            {
              "name": "Rule_Description",
              "ns": "https://oscal-compass/compliance-trestle/schemas/oscal/cd",
              "value": "accounts_passwords_pam_faillock_enabled",
              "remarks": "rule_set_63"
            },
            {
              "name": "Rule_Id",
              "ns": "https://oscal-compass/compliance-trestle/schemas/oscal/cd",
              "value": "accounts_passwords_pam_faillock_root_unlock_time",
              "remarks": "rule_set_64"
            },
            {
              "name": "Rule_Description",
              "ns": "https://oscal-compass/compliance-trestle/schemas/oscal/cd",
              "value": "accounts_passwords_pam_faillock_root_unlock_time",
              "remarks": "rule_set_64"
            },
            {
              "name": "Rule_Id",
              "ns": "https://oscal-compass/compliance-trestle/schemas/oscal/cd",
              "value": "accounts_passwords_pam_faillock_unlock_time",
              "remarks": "rule_set_65"
            },
            {
              "name": "Rule_Description",
              "ns": "https://oscal-compass/compliance-trestle/schemas/oscal/cd",
              "value": "accounts_passwords_pam_faillock_unlock_time",
              "remarks": "rule_set_65"
            },
            {
              "name": "Rule_Id",
              "ns": "https://oscal-compass/compliance-trestle/schemas/oscal/cd",
              "value": "sshd_set_loglevel_info",
              "remarks": "rule_set_66"
            },
            {
              "name": "Rule_Description",
              "ns": "https://oscal-compass/compliance-trestle/schemas/oscal/cd",
              "value": "sshd_set_loglevel_info",
              "remarks": "rule_set_66"
            },
            {
              "name": "Rule_Id",
              "ns": "https://oscal-compass/compliance-trestle/schemas/oscal/cd",
              "value": "sshd_set_max_auth_tries",
              "remarks": "rule_set_67"
            },
            {
              "name": "Rule_Description",
              "ns": "https://oscal-compass/compliance-trestle/schemas/oscal/cd",
              "value": "sshd_set_max_auth_tries",
              "remarks": "rule_set_67"
            },
            {
              "name": "Rule_Id",
              "ns": "https://oscal-compass/compliance-trestle/schemas/oscal/cd",
              "value": "sudo_custom_logfile",
              "remarks": "rule_set_68"
            },
            {
              "name": "Rule_Description",
              "ns": "https://oscal-compass/compliance-trestle/schemas/oscal/cd",
              "value": "sudo_custom_logfile",
              "remarks": "rule_set_68"
            },
            {
              "name": "Rule_Id",
              "ns": "https://oscal-compass/compliance-trestle/schemas/oscal/cd",
              "value": "account_automated_provisioning_enabled",
              "remarks": "rule_set_69"
            },
            {
              "name": "Rule_Description",
              "ns": "https://oscal-compass/compliance-trestle/schemas/oscal/cd",
              "value": "Verify automated account management is configured",
              "remarks": "rule_set_69"
            },
            {
              "name": "Rule_Id",
              "ns": "https://oscal-compass/compliance-trestle/schemas/oscal/cd",
              "value": "account_temporary_expiration_configured",
              "remarks": "rule_set_70"
            },
            {
              "name": "Rule_Description",
              "ns": "https://oscal-compass/compliance-trestle/schemas/oscal/cd",
              "value": "Verify temporary account expiration is automated",
              "remarks": "rule_set_70"
            },
            {
              "name": "Rule_Id",
              "ns": "https://oscal-compass/compliance-trestle/schemas/oscal/cd",
              "value": "account_disable_inactive_accounts",
              "remarks": "rule_set_71"
            },
            {
              "name": "Rule_Description",
              "ns": "https://oscal-compass/compliance-trestle/schemas/oscal/cd",
              "value": "Verify inactive account disabling mechanism",
              "remarks": "rule_set_71"
            },
            {
              "name": "Rule_Id",
              "ns": "https://oscal-compass/compliance-trestle/schemas/oscal/cd",
              "value": "sudo_security_function_authorization",
              "remarks": "rule_set_72"
            },
            {
              "name": "Rule_Description",
              "ns": "https://oscal-compass/compliance-trestle/schemas/oscal/cd",
              "value": "Verify sudo configuration restricts security functions",
              "remarks": "rule_set_72"
            },
            {
              "name": "Rule_Id",
              "ns": "https://oscal-compass/compliance-trestle/schemas/oscal/cd",
              "value": "service_nonprivileged_user_execution",
              "remarks": "rule_set_73"
            },
            {
              "name": "Rule_Description",
              "ns": "https://oscal-compass/compliance-trestle/schemas/oscal/cd",
              "value": "Verify services run as non-root users",
              "remarks": "rule_set_73"
            },
            {
              "name": "Rule_Id",
              "ns": "https://oscal-compass/compliance-trestle/schemas/oscal/cd",
              "value": "screen_lock_timeout_configured",
              "remarks": "rule_set_74"
            },
            {
              "name": "Rule_Description",
              "ns": "https://oscal-compass/compliance-trestle/schemas/oscal/cd",
              "value": "Verify screen lock timeout is configured",
              "remarks": "rule_set_74"
            },
            {
              "name": "Rule_Id",
              "ns": "https://oscal-compass/compliance-trestle/schemas/oscal/cd",
              "value": "screen_lock_pattern_hiding_enabled",
              "remarks": "rule_set_75"
            },
            {
              "name": "Rule_Description",
              "ns": "https://oscal-compass/compliance-trestle/schemas/oscal/cd",
              "value": "Verify screen blanking on lock",
              "remarks": "rule_set_75"
            },
            {
              "name": "Rule_Id",
              "ns": "https://oscal-compass/compliance-trestle/schemas/oscal/cd",
              "value": "sshd_logging_enabled",
              "remarks": "rule_set_76"
            },
            {
              "name": "Rule_Description",
              "ns": "https://oscal-compass/compliance-trestle/schemas/oscal/cd",
              "value": "Verify SSH logging is enabled and comprehensive",
              "remarks": "rule_set_76"
            },
            {
              "name": "Rule_Id",
              "ns": "https://oscal-compass/compliance-trestle/schemas/oscal/cd",
              "value": "auditd_extended_information_enabled",
              "remarks": "rule_set_77"
            },
            {
              "name": "Rule_Description",
              "ns": "https://oscal-compass/compliance-trestle/schemas/oscal/cd",
              "value": "Verify extended audit information is captured",
              "remarks": "rule_set_77"
            },
            {
              "name": "Rule_Id",
              "ns": "https://oscal-compass/compliance-trestle/schemas/oscal/cd",
              "value": "log_analysis_tool_configured",
              "remarks": "rule_set_78"
            },
            {
              "name": "Rule_Description",
              "ns": "https://oscal-compass/compliance-trestle/schemas/oscal/cd",
              "value": "Verify automated log analysis tool is configured",
              "remarks": "rule_set_78"
            },
            {
              "name": "Rule_Id",
              "ns": "https://oscal-compass/compliance-trestle/schemas/oscal/cd",
              "value": "change_control_documentation_required",
              "remarks": "rule_set_79"
            },
            {
              "name": "Rule_Description",
              "ns": "https://oscal-compass/compliance-trestle/schemas/oscal/cd",
              "value": "Verify change control process documentation",
              "remarks": "rule_set_79"
            },
            {
              "name": "Rule_Id",
              "ns": "https://oscal-compass/compliance-trestle/schemas/oscal/cd",
              "value": "service_periodic_review_enabled",
              "remarks": "rule_set_80"
            },
            {
              "name": "Rule_Description",
              "ns": "https://oscal-compass/compliance-trestle/schemas/oscal/cd",
              "value": "Verify periodic service review process",
              "remarks": "rule_set_80"
            },
            {
              "name": "Rule_Id",
              "ns": "https://oscal-compass/compliance-trestle/schemas/oscal/cd",
              "value": "package_update_automation_configured",
              "remarks": "rule_set_81"
            },
            {
              "name": "Rule_Description",
              "ns": "https://oscal-compass/compliance-trestle/schemas/oscal/cd",
              "value": "Verify automated patch management",
              "remarks": "rule_set_81"
            },
            {
              "name": "Rule_Id",
              "ns": "https://oscal-compass/compliance-trestle/schemas/oscal/cd",
              "value": "intrusion_detection_tool_installed",
              "remarks": "rule_set_82"
            },
            {
              "name": "Rule_Description",
              "ns": "https://oscal-compass/compliance-trestle/schemas/oscal/cd",
              "value": "Verify IDS/IPS tool is installed and running",
              "remarks": "rule_set_82"
            },
            {
              "name": "Rule_Id",
              "ns": "https://oscal-compass/compliance-trestle/schemas/oscal/cd",
              "value": "encrypted_traffic_inspection_configured",
              "remarks": "rule_set_83"
            },
            {
              "name": "Rule_Description",
              "ns": "https://oscal-compass/compliance-trestle/schemas/oscal/cd",
              "value": "Verify encrypted traffic inspection capability",
              "remarks": "rule_set_83"
            },
            {
              "name": "Rule_Id",
              "ns": "https://oscal-compass/compliance-trestle/schemas/oscal/cd",
              "value": "privileged_command_network_restriction",
              "remarks": "rule_set_84"
            },
            {
              "name": "Rule_Description",
              "ns": "https://oscal-compass/compliance-trestle/schemas/oscal/cd",
              "value": "Verify network-based restrictions on privileged commands",
              "remarks": "rule_set_84"
            },
            {
              "name": "Rule_Id",
              "ns": "https://oscal-compass/compliance-trestle/schemas/oscal/cd",
              "value": "concurrent_session_limit_configured",
              "remarks": "rule_set_85"
            },
            {
              "name": "Rule_Description",
              "ns": "https://oscal-compass/compliance-trestle/schemas/oscal/cd",
              "value": "Verify concurrent session limits",
              "remarks": "rule_set_85"
            },
            {
              "name": "Rule_Id",
              "ns": "https://oscal-compass/compliance-trestle/schemas/oscal/cd",
              "value": "auditd_storage_threshold_alert",
              "remarks": "rule_set_86"
            },
            {
              "name": "Rule_Description",
              "ns": "https://oscal-compass/compliance-trestle/schemas/oscal/cd",
              "value": "Verify audit storage threshold alerting",
              "remarks": "rule_set_86"
            },
            {
              "name": "Rule_Id",
              "ns": "https://oscal-compass/compliance-trestle/schemas/oscal/cd",
              "value": "auditd_realtime_alerts_enabled",
              "remarks": "rule_set_87"
            },
            {
              "name": "Rule_Description",
              "ns": "https://oscal-compass/compliance-trestle/schemas/oscal/cd",
              "value": "Verify real-time audit failure alerts",
              "remarks": "rule_set_87"
            },
            {
              "name": "Rule_Id",
              "ns": "https://oscal-compass/compliance-trestle/schemas/oscal/cd",
              "value": "centralized_logging_configured",
              "remarks": "rule_set_88"
            },
            {
              "name": "Rule_Description",
              "ns": "https://oscal-compass/compliance-trestle/schemas/oscal/cd",
              "value": "Verify centralized logging is configured",
              "remarks": "rule_set_88"
            },
            {
              "name": "Rule_Id",
              "ns": "https://oscal-compass/compliance-trestle/schemas/oscal/cd",
              "value": "audit_logs_remote_storage",
              "remarks": "rule_set_89"
            },
            {
              "name": "Rule_Description",
              "ns": "https://oscal-compass/compliance-trestle/schemas/oscal/cd",
              "value": "Verify audit logs are sent to remote system",
              "remarks": "rule_set_89"
            },
            {
              "name": "Rule_Id",
              "ns": "https://oscal-compass/compliance-trestle/schemas/oscal/cd",
              "value": "audit_logs_encrypted",
              "remarks": "rule_set_90"
            },
            {
              "name": "Rule_Description",
              "ns": "https://oscal-compass/compliance-trestle/schemas/oscal/cd",
              "value": "Verify audit log encryption/signing",
              "remarks": "rule_set_90"
            },
            {
              "name": "Rule_Id",
              "ns": "https://oscal-compass/compliance-trestle/schemas/oscal/cd",
              "value": "critical_action_signing_enabled",
              "remarks": "rule_set_91"
            },
            {
              "name": "Rule_Description",
              "ns": "https://oscal-compass/compliance-trestle/schemas/oscal/cd",
              "value": "Verify digital signatures for critical actions",
              "remarks": "rule_set_91"
            },
            {
              "name": "Rule_Id",
              "ns": "https://oscal-compass/compliance-trestle/schemas/oscal/cd",
              "value": "time_synchronization_configured",
              "remarks": "rule_set_92"
            },
            {
              "name": "Rule_Description",
              "ns": "https://oscal-compass/compliance-trestle/schemas/oscal/cd",
              "value": "Verify NTP/chrony is configured and running",
              "remarks": "rule_set_92"
            }
          ],
          "status": {
            "state": "operational"
          }
        }
      ],
      "inventory-items": [
        {
          "uuid": "a8377819-76d0-4980-ae71-dd1bae0551d4",
          "description": "Application server running Ubuntu 24.04 LTS",
          "props": [
            {
              "name": "asset-id",
              "value": "ubuntu-app-01.example.com"
            },
            {
              "name": "asset-type",
              "value": "server"
            },
            {
              "name": "ipv4-address",
              "value": "192.168.1.104"
            },
            {
              "name": "role",
              "value": "application-server"
            },
            {
              "name": "operating-system",
              "value": "Ubuntu 24.04 LTS"
            }
          ],
          "implemented-components": [
            {
              "component-uuid": "b2e11579-d4d6-48f8-a43c-ec7157543648"
            }
          ]
        },
        {
          "uuid": "25303d97-bd46-438c-9fc5-eea66a12944a",
          "description": "Database server running Ubuntu 24.04 LTS",
          "props": [
            {
              "name": "asset-id",
              "value": "ubuntu-db-01.example.com"
            },
            {
              "name": "asset-type",
              "value": "server"
            },
            {
              "name": "ipv4-address",
              "value": "192.168.1.103"
            },
            {
              "name": "role",
              "value": "database-server"
            },
            {
              "name": "operating-system",
              "value": "Ubuntu 24.04 LTS"
            }
          ],
          "implemented-components": [
            {
              "component-uuid": "b2e11579-d4d6-48f8-a43c-ec7157543648"
            }
          ]
        },
        {
          "uuid": "9784e082-84f2-40d2-873c-0d957c35c71e",
          "description": "Management and monitoring server running Ubuntu 24.04 LTS",
          "props": [
            {
              "name": "asset-id",
              "value": "ubuntu-mgmt-01.example.com"
            },
            {
              "name": "asset-type",
              "value": "server"
            },
            {
              "name": "ipv4-address",
              "value": "192.168.1.105"
            },
            {
              "name": "role",
              "value": "management-server"
            },
            {
              "name": "operating-system",
              "value": "Ubuntu 24.04 LTS"
            }
          ],
          "implemented-components": [
            {
              "component-uuid": "b2e11579-d4d6-48f8-a43c-ec7157543648"
            }
          ]
        },
        {
          "uuid": "55298391-e799-4b7b-a4b1-89d05e87d4e4",
          "description": "Primary web server running Ubuntu 24.04 LTS",
          "props": [
            {
              "name": "asset-id",
              "value": "ubuntu-web-01.example.com"
            },
            {
              "name": "asset-type",
              "value": "server"
            },
            {
              "name": "ipv4-address",
              "value": "192.168.1.101"
            },
            {
              "name": "role",
              "value": "web-server"
            },
            {
              "name": "operating-system",
              "value": "Ubuntu 24.04 LTS"
            }
          ],
          "implemented-components": [
            {
              "component-uuid": "b2e11579-d4d6-48f8-a43c-ec7157543648"
            }
          ]
        },
        {
          "uuid": "8894c0ef-2565-405a-8ba5-e9ec64188718",
          "description": "Secondary web server running Ubuntu 24.04 LTS",
          "props": [
            {
              "name": "asset-id",
              "value": "ubuntu-web-02.example.com"
            },
            {
              "name": "asset-type",
              "value": "server"
            },
            {
              "name": "ipv4-address",
              "value": "192.168.1.102"
            },
            {
              "name": "role",
              "value": "web-server"
            },
            {
              "name": "operating-system",
              "value": "Ubuntu 24.04 LTS"
            }
          ],
          "implemented-components": [
            {
              "component-uuid": "b2e11579-d4d6-48f8-a43c-ec7157543648"
            }
          ]
        },
        {
          "uuid": "5f7727b4-a8fb-42c1-b2e4-afe7e0a02668",
          "description": "Tertiary web server running Ubuntu 24.04 LTS",
          "props": [
            {
              "name": "asset-id",
              "value": "ubuntu-web-03.example.com"
            },
            {
              "name": "asset-type",
              "value": "server"
            },
            {
              "name": "ipv4-address",
              "value": "192.168.1.106"
            },
            {
              "name": "role",
              "value": "web-server"
            },
            {
              "name": "operating-system",
              "value": "Ubuntu 24.04 LTS"
            }
          ],
          "implemented-components": [
            {
              "component-uuid": "b2e11579-d4d6-48f8-a43c-ec7157543648"
            }
          ]
        }
      ]
    },
    "control-implementation": {
      "description": "Control implementation for FedRAMP Moderate baseline using Ubuntu Linux 24.04 LTS",
      "implemented-requirements": [
        {
          "uuid": "4cc2c99d-ff55-4366-a5a8-32ad9997bd5d",
          "control-id": "ac-3",
          "props": [
            {
              "name": "Rule_Id",
              "ns": "https://oscal-compass/compliance-trestle/schemas/oscal/cd",
              "value": "accounts_password_pam_unix_enabled"
            },
            {
              "name": "Rule_Id",
              "ns": "https://oscal-compass/compliance-trestle/schemas/oscal/cd",
              "value": "accounts_root_gid_zero"
            },
            {
              "name": "Rule_Id",
              "ns": "https://oscal-compass/compliance-trestle/schemas/oscal/cd",
              "value": "accounts_umask_etc_bashrc"
            },
            {
              "name": "Rule_Id",
              "ns": "https://oscal-compass/compliance-trestle/schemas/oscal/cd",
              "value": "accounts_umask_etc_login_defs"
            },
            {
              "name": "Rule_Id",
              "ns": "https://oscal-compass/compliance-trestle/schemas/oscal/cd",
              "value": "accounts_umask_etc_profile"
            },
            {
              "name": "Rule_Id",
              "ns": "https://oscal-compass/compliance-trestle/schemas/oscal/cd",
              "value": "accounts_umask_root"
            },
            {
              "name": "Rule_Id",
              "ns": "https://oscal-compass/compliance-trestle/schemas/oscal/cd",
              "value": "ensure_pam_wheel_group_empty"
            },
            {
              "name": "Rule_Id",
              "ns": "https://oscal-compass/compliance-trestle/schemas/oscal/cd",
              "value": "ensure_root_access_controlled"
            },
            {
              "name": "Rule_Id",
              "ns": "https://oscal-compass/compliance-trestle/schemas/oscal/cd",
              "value": "file_groupowner_sshd_config"
            },
            {
              "name": "Rule_Id",
              "ns": "https://oscal-compass/compliance-trestle/schemas/oscal/cd",
              "value": "file_owner_sshd_config"
            },
            {
              "name": "Rule_Id",
              "ns": "https://oscal-compass/compliance-trestle/schemas/oscal/cd",
              "value": "file_permissions_sshd_config"
            },
            {
              "name": "Rule_Id",
              "ns": "https://oscal-compass/compliance-trestle/schemas/oscal/cd",
              "value": "file_permissions_sshd_private_key"
            },
            {
              "name": "Rule_Id",
              "ns": "https://oscal-compass/compliance-trestle/schemas/oscal/cd",
              "value": "file_permissions_sshd_pub_key"
            },
            {
              "name": "Rule_Id",
              "ns": "https://oscal-compass/compliance-trestle/schemas/oscal/cd",
              "value": "groups_no_zero_gid_except_root"
            },
            {
              "name": "Rule_Id",
              "ns": "https://oscal-compass/compliance-trestle/schemas/oscal/cd",
              "value": "no_invalid_shell_accounts_unlocked"
            },
            {
              "name": "Rule_Id",
              "ns": "https://oscal-compass/compliance-trestle/schemas/oscal/cd",
              "value": "no_shelllogin_for_systemaccounts"
            },
            {
              "name": "Rule_Id",
              "ns": "https://oscal-compass/compliance-trestle/schemas/oscal/cd",
              "value": "sshd_limit_user_access"
            },
            {
              "name": "Rule_Id",
              "ns": "https://oscal-compass/compliance-trestle/schemas/oscal/cd",
              "value": "use_pam_wheel_group_for_su"
            }
          ]
        },
        {
          "uuid": "60c5eed8-36ef-4966-8a6f-06e0dc08cb4d",
          "control-id": "ac-5",
          "props": [
            {
              "name": "Rule_Id",
              "ns": "https://oscal-compass/compliance-trestle/schemas/oscal/cd",
              "value": "accounts_password_pam_unix_enabled"
            },
            {
              "name": "Rule_Id",
              "ns": "https://oscal-compass/compliance-trestle/schemas/oscal/cd",
              "value": "accounts_root_gid_zero"
            },
            {
              "name": "Rule_Id",
              "ns": "https://oscal-compass/compliance-trestle/schemas/oscal/cd",
              "value": "accounts_umask_etc_bashrc"
            },
            {
              "name": "Rule_Id",
              "ns": "https://oscal-compass/compliance-trestle/schemas/oscal/cd",
              "value": "accounts_umask_etc_login_defs"
            },
            {
              "name": "Rule_Id",
              "ns": "https://oscal-compass/compliance-trestle/schemas/oscal/cd",
              "value": "accounts_umask_etc_profile"
            },
            {
              "name": "Rule_Id",
              "ns": "https://oscal-compass/compliance-trestle/schemas/oscal/cd",
              "value": "accounts_umask_root"
            },
            {
              "name": "Rule_Id",
              "ns": "https://oscal-compass/compliance-trestle/schemas/oscal/cd",
              "value": "ensure_pam_wheel_group_empty"
            },
            {
              "name": "Rule_Id",
              "ns": "https://oscal-compass/compliance-trestle/schemas/oscal/cd",
              "value": "ensure_root_access_controlled"
            },
            {
              "name": "Rule_Id",
              "ns": "https://oscal-compass/compliance-trestle/schemas/oscal/cd",
              "value": "file_groupowner_sshd_config"
            },
            {
              "name": "Rule_Id",
              "ns": "https://oscal-compass/compliance-trestle/schemas/oscal/cd",
              "value": "file_owner_sshd_config"
            },
            {
              "name": "Rule_Id",
              "ns": "https://oscal-compass/compliance-trestle/schemas/oscal/cd",
              "value": "file_permissions_sshd_config"
            },
            {
              "name": "Rule_Id",
              "ns": "https://oscal-compass/compliance-trestle/schemas/oscal/cd",
              "value": "file_permissions_sshd_private_key"
            },
            {
              "name": "Rule_Id",
              "ns": "https://oscal-compass/compliance-trestle/schemas/oscal/cd",
              "value": "file_permissions_sshd_pub_key"
            },
            {
              "name": "Rule_Id",
              "ns": "https://oscal-compass/compliance-trestle/schemas/oscal/cd",
              "value": "groups_no_zero_gid_except_root"
            },
            {
              "name": "Rule_Id",
              "ns": "https://oscal-compass/compliance-trestle/schemas/oscal/cd",
              "value": "no_invalid_shell_accounts_unlocked"
            },
            {
              "name": "Rule_Id",
              "ns": "https://oscal-compass/compliance-trestle/schemas/oscal/cd",
              "value": "no_shelllogin_for_systemaccounts"
            },
            {
              "name": "Rule_Id",
              "ns": "https://oscal-compass/compliance-trestle/schemas/oscal/cd",
              "value": "sshd_limit_user_access"
            },
            {
              "name": "Rule_Id",
              "ns": "https://oscal-compass/compliance-trestle/schemas/oscal/cd",
              "value": "use_pam_wheel_group_for_su"
            }
          ]
        },
        {
          "uuid": "1af9ae67-ce2a-4385-8c13-deeef4d542b8",
          "control-id": "ac-6",
          "props": [
            {
              "name": "Rule_Id",
              "ns": "https://oscal-compass/compliance-trestle/schemas/oscal/cd",
              "value": "accounts_password_pam_unix_enabled"
            },
            {
              "name": "Rule_Id",
              "ns": "https://oscal-compass/compliance-trestle/schemas/oscal/cd",
              "value": "accounts_root_gid_zero"
            },
            {
              "name": "Rule_Id",
              "ns": "https://oscal-compass/compliance-trestle/schemas/oscal/cd",
              "value": "accounts_umask_etc_bashrc"
            },
            {
              "name": "Rule_Id",
              "ns": "https://oscal-compass/compliance-trestle/schemas/oscal/cd",
              "value": "accounts_umask_etc_login_defs"
            },
            {
              "name": "Rule_Id",
              "ns": "https://oscal-compass/compliance-trestle/schemas/oscal/cd",
              "value": "accounts_umask_etc_profile"
            },
            {
              "name": "Rule_Id",
              "ns": "https://oscal-compass/compliance-trestle/schemas/oscal/cd",
              "value": "accounts_umask_root"
            },
            {
              "name": "Rule_Id",
              "ns": "https://oscal-compass/compliance-trestle/schemas/oscal/cd",
              "value": "ensure_pam_wheel_group_empty"
            },
            {
              "name": "Rule_Id",
              "ns": "https://oscal-compass/compliance-trestle/schemas/oscal/cd",
              "value": "ensure_root_access_controlled"
            },
            {
              "name": "Rule_Id",
              "ns": "https://oscal-compass/compliance-trestle/schemas/oscal/cd",
              "value": "file_groupowner_sshd_config"
            },
            {
              "name": "Rule_Id",
              "ns": "https://oscal-compass/compliance-trestle/schemas/oscal/cd",
              "value": "file_owner_sshd_config"
            },
            {
              "name": "Rule_Id",
              "ns": "https://oscal-compass/compliance-trestle/schemas/oscal/cd",
              "value": "file_permissions_sshd_config"
            },
            {
              "name": "Rule_Id",
              "ns": "https://oscal-compass/compliance-trestle/schemas/oscal/cd",
              "value": "file_permissions_sshd_private_key"
            },
            {
              "name": "Rule_Id",
              "ns": "https://oscal-compass/compliance-trestle/schemas/oscal/cd",
              "value": "file_permissions_sshd_pub_key"
            },
            {
              "name": "Rule_Id",
              "ns": "https://oscal-compass/compliance-trestle/schemas/oscal/cd",
              "value": "groups_no_zero_gid_except_root"
            },
            {
              "name": "Rule_Id",
              "ns": "https://oscal-compass/compliance-trestle/schemas/oscal/cd",
              "value": "no_invalid_shell_accounts_unlocked"
            },
            {
              "name": "Rule_Id",
              "ns": "https://oscal-compass/compliance-trestle/schemas/oscal/cd",
              "value": "no_shelllogin_for_systemaccounts"
            },
            {
              "name": "Rule_Id",
              "ns": "https://oscal-compass/compliance-trestle/schemas/oscal/cd",
              "value": "sshd_limit_user_access"
            },
            {
              "name": "Rule_Id",
              "ns": "https://oscal-compass/compliance-trestle/schemas/oscal/cd",
              "value": "use_pam_wheel_group_for_su"
            }
          ]
        },
        {
          "uuid": "3df9808c-b4b5-49ba-b1ae-a30f8c364898",
          "control-id": "mp-2",
          "props": [
            {
              "name": "Rule_Id",
              "ns": "https://oscal-compass/compliance-trestle/schemas/oscal/cd",
              "value": "accounts_password_pam_unix_enabled"
            },
            {
              "name": "Rule_Id",
              "ns": "https://oscal-compass/compliance-trestle/schemas/oscal/cd",
              "value": "accounts_root_gid_zero"
            },
            {
              "name": "Rule_Id",
              "ns": "https://oscal-compass/compliance-trestle/schemas/oscal/cd",
              "value": "accounts_umask_etc_bashrc"
            },
            {
              "name": "Rule_Id",
              "ns": "https://oscal-compass/compliance-trestle/schemas/oscal/cd",
              "value": "accounts_umask_etc_login_defs"
            },
            {
              "name": "Rule_Id",
              "ns": "https://oscal-compass/compliance-trestle/schemas/oscal/cd",
              "value": "accounts_umask_etc_profile"
            },
            {
              "name": "Rule_Id",
              "ns": "https://oscal-compass/compliance-trestle/schemas/oscal/cd",
              "value": "accounts_umask_root"
            },
            {
              "name": "Rule_Id",
              "ns": "https://oscal-compass/compliance-trestle/schemas/oscal/cd",
              "value": "ensure_pam_wheel_group_empty"
            },
            {
              "name": "Rule_Id",
              "ns": "https://oscal-compass/compliance-trestle/schemas/oscal/cd",
              "value": "ensure_root_access_controlled"
            },
            {
              "name": "Rule_Id",
              "ns": "https://oscal-compass/compliance-trestle/schemas/oscal/cd",
              "value": "file_groupowner_sshd_config"
            },
            {
              "name": "Rule_Id",
              "ns": "https://oscal-compass/compliance-trestle/schemas/oscal/cd",
              "value": "file_owner_sshd_config"
            },
            {
              "name": "Rule_Id",
              "ns": "https://oscal-compass/compliance-trestle/schemas/oscal/cd",
              "value": "file_permissions_sshd_config"
            },
            {
              "name": "Rule_Id",
              "ns": "https://oscal-compass/compliance-trestle/schemas/oscal/cd",
              "value": "file_permissions_sshd_private_key"
            },
            {
              "name": "Rule_Id",
              "ns": "https://oscal-compass/compliance-trestle/schemas/oscal/cd",
              "value": "file_permissions_sshd_pub_key"
            },
            {
              "name": "Rule_Id",
              "ns": "https://oscal-compass/compliance-trestle/schemas/oscal/cd",
              "value": "groups_no_zero_gid_except_root"
            },
            {
              "name": "Rule_Id",
              "ns": "https://oscal-compass/compliance-trestle/schemas/oscal/cd",
              "value": "no_invalid_shell_accounts_unlocked"
            },
            {
              "name": "Rule_Id",
              "ns": "https://oscal-compass/compliance-trestle/schemas/oscal/cd",
              "value": "no_shelllogin_for_systemaccounts"
            },
            {
              "name": "Rule_Id",
              "ns": "https://oscal-compass/compliance-trestle/schemas/oscal/cd",
              "value": "sshd_limit_user_access"
            },
            {
              "name": "Rule_Id",
              "ns": "https://oscal-compass/compliance-trestle/schemas/oscal/cd",
              "value": "use_pam_wheel_group_for_su"
            }
          ]
        },
        {
          "uuid": "8fe3c2b3-880a-470d-bcb4-d97aba5a2b90",
          "control-id": "ac-17.2",
          "props": [
            {
              "name": "Rule_Id",
              "ns": "https://oscal-compass/compliance-trestle/schemas/oscal/cd",
              "value": "sshd_use_strong_ciphers"
            },
            {
              "name": "Rule_Id",
              "ns": "https://oscal-compass/compliance-trestle/schemas/oscal/cd",
              "value": "sshd_use_strong_kex"
            },
            {
              "name": "Rule_Id",
              "ns": "https://oscal-compass/compliance-trestle/schemas/oscal/cd",
              "value": "sshd_use_strong_macs"
            }
          ]
        },
        {
          "uuid": "a2b8aaa3-f92b-47a7-b87a-0ddb93f164da",
          "control-id": "ia-5",
          "props": [
            {
              "name": "Rule_Id",
              "ns": "https://oscal-compass/compliance-trestle/schemas/oscal/cd",
              "value": "sshd_use_strong_ciphers"
            },
            {
              "name": "Rule_Id",
              "ns": "https://oscal-compass/compliance-trestle/schemas/oscal/cd",
              "value": "sshd_use_strong_kex"
            },
            {
              "name": "Rule_Id",
              "ns": "https://oscal-compass/compliance-trestle/schemas/oscal/cd",
              "value": "sshd_use_strong_macs"
            }
          ]
        },
        {
          "uuid": "7000a1d9-6f57-4bb2-8a99-9322524e79df",
          "control-id": "ia-5.1",
          "props": [
            {
              "name": "Rule_Id",
              "ns": "https://oscal-compass/compliance-trestle/schemas/oscal/cd",
              "value": "sshd_use_strong_ciphers"
            },
            {
              "name": "Rule_Id",
              "ns": "https://oscal-compass/compliance-trestle/schemas/oscal/cd",
              "value": "sshd_use_strong_kex"
            },
            {
              "name": "Rule_Id",
              "ns": "https://oscal-compass/compliance-trestle/schemas/oscal/cd",
              "value": "sshd_use_strong_macs"
            },
            {
              "name": "Rule_Id",
              "ns": "https://oscal-compass/compliance-trestle/schemas/oscal/cd",
              "value": "accounts_password_pam_pwhistory_use_authtok"
            },
            {
              "name": "Rule_Id",
              "ns": "https://oscal-compass/compliance-trestle/schemas/oscal/cd",
              "value": "accounts_password_pam_unix_authtok"
            },
            {
              "name": "Rule_Id",
              "ns": "https://oscal-compass/compliance-trestle/schemas/oscal/cd",
              "value": "set_password_hashing_algorithm_logindefs"
            },
            {
              "name": "Rule_Id",
              "ns": "https://oscal-compass/compliance-trestle/schemas/oscal/cd",
              "value": "set_password_hashing_algorithm_systemauth"
            },
            {
              "name": "Rule_Id",
              "ns": "https://oscal-compass/compliance-trestle/schemas/oscal/cd",
              "value": "account_disable_post_pw_expiration"
            },
            {
              "name": "Rule_Id",
              "ns": "https://oscal-compass/compliance-trestle/schemas/oscal/cd",
              "value": "accounts_maximum_age_login_defs"
            },
            {
              "name": "Rule_Id",
              "ns": "https://oscal-compass/compliance-trestle/schemas/oscal/cd",
              "value": "accounts_minimum_age_login_defs"
            },
            {
              "name": "Rule_Id",
              "ns": "https://oscal-compass/compliance-trestle/schemas/oscal/cd",
              "value": "accounts_password_last_change_is_in_past"
            },
            {
              "name": "Rule_Id",
              "ns": "https://oscal-compass/compliance-trestle/schemas/oscal/cd",
              "value": "accounts_password_pam_dcredit"
            },
            {
              "name": "Rule_Id",
              "ns": "https://oscal-compass/compliance-trestle/schemas/oscal/cd",
              "value": "accounts_password_pam_dictcheck"
            },
            {
              "name": "Rule_Id",
              "ns": "https://oscal-compass/compliance-trestle/schemas/oscal/cd",
              "value": "accounts_password_pam_difok"
            },
            {
              "name": "Rule_Id",
              "ns": "https://oscal-compass/compliance-trestle/schemas/oscal/cd",
              "value": "accounts_password_pam_enforce_root"
            },
            {
              "name": "Rule_Id",
              "ns": "https://oscal-compass/compliance-trestle/schemas/oscal/cd",
              "value": "accounts_password_pam_enforcing"
            },
            {
              "name": "Rule_Id",
              "ns": "https://oscal-compass/compliance-trestle/schemas/oscal/cd",
              "value": "accounts_password_pam_lcredit"
            },
            {
              "name": "Rule_Id",
              "ns": "https://oscal-compass/compliance-trestle/schemas/oscal/cd",
              "value": "accounts_password_pam_maxrepeat"
            },
            {
              "name": "Rule_Id",
              "ns": "https://oscal-compass/compliance-trestle/schemas/oscal/cd",
              "value": "accounts_password_pam_maxsequence"
            },
            {
              "name": "Rule_Id",
              "ns": "https://oscal-compass/compliance-trestle/schemas/oscal/cd",
              "value": "accounts_password_pam_minclass"
            },
            {
              "name": "Rule_Id",
              "ns": "https://oscal-compass/compliance-trestle/schemas/oscal/cd",
              "value": "accounts_password_pam_minlen"
            },
            {
              "name": "Rule_Id",
              "ns": "https://oscal-compass/compliance-trestle/schemas/oscal/cd",
              "value": "accounts_password_pam_ocredit"
            },
            {
              "name": "Rule_Id",
              "ns": "https://oscal-compass/compliance-trestle/schemas/oscal/cd",
              "value": "accounts_password_pam_pwhistory_enabled"
            },
            {
              "name": "Rule_Id",
              "ns": "https://oscal-compass/compliance-trestle/schemas/oscal/cd",
              "value": "accounts_password_pam_pwhistory_enforce_root"
            },
            {
              "name": "Rule_Id",
              "ns": "https://oscal-compass/compliance-trestle/schemas/oscal/cd",
              "value": "accounts_password_pam_pwhistory_remember"
            },
            {
              "name": "Rule_Id",
              "ns": "https://oscal-compass/compliance-trestle/schemas/oscal/cd",
              "value": "accounts_password_pam_pwquality_enabled"
            },
            {
              "name": "Rule_Id",
              "ns": "https://oscal-compass/compliance-trestle/schemas/oscal/cd",
              "value": "accounts_password_pam_ucredit"
            },
            {
              "name": "Rule_Id",
              "ns": "https://oscal-compass/compliance-trestle/schemas/oscal/cd",
              "value": "accounts_password_pam_unix_no_remember"
            },
            {
              "name": "Rule_Id",
              "ns": "https://oscal-compass/compliance-trestle/schemas/oscal/cd",
              "value": "accounts_password_set_max_life_existing"
            },
            {
              "name": "Rule_Id",
              "ns": "https://oscal-compass/compliance-trestle/schemas/oscal/cd",
              "value": "accounts_password_set_min_life_existing"
            },
            {
              "name": "Rule_Id",
              "ns": "https://oscal-compass/compliance-trestle/schemas/oscal/cd",
              "value": "no_empty_passwords_unix"
            },
            {
              "name": "Rule_Id",
              "ns": "https://oscal-compass/compliance-trestle/schemas/oscal/cd",
              "value": "sshd_disable_empty_passwords"
            },
            {
              "name": "Rule_Id",
              "ns": "https://oscal-compass/compliance-trestle/schemas/oscal/cd",
              "value": "sshd_disable_gssapi_auth"
            },
            {
              "name": "Rule_Id",
              "ns": "https://oscal-compass/compliance-trestle/schemas/oscal/cd",
              "value": "sshd_disable_rhosts"
            },
            {
              "name": "Rule_Id",
              "ns": "https://oscal-compass/compliance-trestle/schemas/oscal/cd",
              "value": "sshd_enable_pam"
            }
          ]
        },
        {
          "uuid": "26514dd2-78a4-4e09-b3d1-d2cda0b9031a",
          "control-id": "sc-8",
          "props": [
            {
              "name": "Rule_Id",
              "ns": "https://oscal-compass/compliance-trestle/schemas/oscal/cd",
              "value": "sshd_use_strong_ciphers"
            },
            {
              "name": "Rule_Id",
              "ns": "https://oscal-compass/compliance-trestle/schemas/oscal/cd",
              "value": "sshd_use_strong_kex"
            },
            {
              "name": "Rule_Id",
              "ns": "https://oscal-compass/compliance-trestle/schemas/oscal/cd",
              "value": "sshd_use_strong_macs"
            }
          ]
        },
        {
          "uuid": "f263444d-aeff-4236-8efd-349ad56787a6",
          "control-id": "sc-8.1",
          "props": [
            {
              "name": "Rule_Id",
              "ns": "https://oscal-compass/compliance-trestle/schemas/oscal/cd",
              "value": "sshd_use_strong_ciphers"
            },
            {
              "name": "Rule_Id",
              "ns": "https://oscal-compass/compliance-trestle/schemas/oscal/cd",
              "value": "sshd_use_strong_kex"
            },
            {
              "name": "Rule_Id",
              "ns": "https://oscal-compass/compliance-trestle/schemas/oscal/cd",
              "value": "sshd_use_strong_macs"
            }
          ]
        },
        {
          "uuid": "e4b56ff0-1eeb-4c3e-80ca-9deb1ca88193",
          "control-id": "sc-28",
          "props": [
            {
              "name": "Rule_Id",
              "ns": "https://oscal-compass/compliance-trestle/schemas/oscal/cd",
              "value": "accounts_password_pam_pwhistory_use_authtok"
            },
            {
              "name": "Rule_Id",
              "ns": "https://oscal-compass/compliance-trestle/schemas/oscal/cd",
              "value": "accounts_password_pam_unix_authtok"
            },
            {
              "name": "Rule_Id",
              "ns": "https://oscal-compass/compliance-trestle/schemas/oscal/cd",
              "value": "set_password_hashing_algorithm_logindefs"
            },
            {
              "name": "Rule_Id",
              "ns": "https://oscal-compass/compliance-trestle/schemas/oscal/cd",
              "value": "set_password_hashing_algorithm_systemauth"
            }
          ]
        },
        {
          "uuid": "bdd7db8b-343d-4946-8d03-7e4c89b9fad1",
          "control-id": "sc-28.1",
          "props": [
            {
              "name": "Rule_Id",
              "ns": "https://oscal-compass/compliance-trestle/schemas/oscal/cd",
              "value": "accounts_password_pam_pwhistory_use_authtok"
            },
            {
              "name": "Rule_Id",
              "ns": "https://oscal-compass/compliance-trestle/schemas/oscal/cd",
              "value": "accounts_password_pam_unix_authtok"
            },
            {
              "name": "Rule_Id",
              "ns": "https://oscal-compass/compliance-trestle/schemas/oscal/cd",
              "value": "set_password_hashing_algorithm_logindefs"
            },
            {
              "name": "Rule_Id",
              "ns": "https://oscal-compass/compliance-trestle/schemas/oscal/cd",
              "value": "set_password_hashing_algorithm_systemauth"
            }
          ]
        },
        {
          "uuid": "687990a3-2be5-4603-a4cf-7f6fd6ea726a",
          "control-id": "cm-1",
          "props": [
            {
              "name": "Rule_Id",
              "ns": "https://oscal-compass/compliance-trestle/schemas/oscal/cd",
              "value": "accounts_password_warn_age_login_defs"
            }
          ]
        },
        {
          "uuid": "6664434c-77c1-4c08-9ca8-2644b398efec",
          "control-id": "cm-2",
          "props": [
            {
              "name": "Rule_Id",
              "ns": "https://oscal-compass/compliance-trestle/schemas/oscal/cd",
              "value": "accounts_password_warn_age_login_defs"
            }
          ]
        },
        {
          "uuid": "ca0e6014-8a54-48c3-a39b-e0aab15c7ca2",
          "control-id": "cm-6",
          "props": [
            {
              "name": "Rule_Id",
              "ns": "https://oscal-compass/compliance-trestle/schemas/oscal/cd",
              "value": "accounts_password_warn_age_login_defs"
            },
            {
              "name": "Rule_Id",
              "ns": "https://oscal-compass/compliance-trestle/schemas/oscal/cd",
              "value": "sshd_disable_forwarding"
            }
          ]
        },
        {
          "uuid": "7ba30d96-cc14-46f8-b1c4-30661714ae11",
          "control-id": "cm-7",
          "props": [
            {
              "name": "Rule_Id",
              "ns": "https://oscal-compass/compliance-trestle/schemas/oscal/cd",
              "value": "accounts_password_warn_age_login_defs"
            },
            {
              "name": "Rule_Id",
              "ns": "https://oscal-compass/compliance-trestle/schemas/oscal/cd",
              "value": "sshd_disable_forwarding"
            }
          ]
        },
        {
          "uuid": "84f88f0b-407d-4b7a-aae0-2beadbb5cf9b",
          "control-id": "cm-7.1",
          "props": [
            {
              "name": "Rule_Id",
              "ns": "https://oscal-compass/compliance-trestle/schemas/oscal/cd",
              "value": "accounts_password_warn_age_login_defs"
            }
          ]
        },
        {
          "uuid": "a40c02f1-82d9-45b5-a293-c6c546f0affc",
          "control-id": "cm-9",
          "props": [
            {
              "name": "Rule_Id",
              "ns": "https://oscal-compass/compliance-trestle/schemas/oscal/cd",
              "value": "accounts_password_warn_age_login_defs"
            }
          ]
        },
        {
          "uuid": "878ea758-b08e-483f-93f8-80f2093fe3d5",
          "control-id": "sa-3",
          "props": [
            {
              "name": "Rule_Id",
              "ns": "https://oscal-compass/compliance-trestle/schemas/oscal/cd",
              "value": "accounts_password_warn_age_login_defs"
            }
          ]
        },
        {
          "uuid": "b8855e08-9b98-48e9-bb27-8f161e9328db",
          "control-id": "sa-8",
          "props": [
            {
              "name": "Rule_Id",
              "ns": "https://oscal-compass/compliance-trestle/schemas/oscal/cd",
              "value": "accounts_password_warn_age_login_defs"
            }
          ]
        },
        {
          "uuid": "7ce39036-6b62-4969-ab2c-19b7bc5bbaf9",
          "control-id": "sa-10",
          "props": [
            {
              "name": "Rule_Id",
              "ns": "https://oscal-compass/compliance-trestle/schemas/oscal/cd",
              "value": "accounts_password_warn_age_login_defs"
            }
          ]
        },
        {
          "uuid": "d2f78ef4-e197-43b1-b225-305b4d77de8b",
          "control-id": "ac-2.5",
          "props": [
            {
              "name": "Rule_Id",
              "ns": "https://oscal-compass/compliance-trestle/schemas/oscal/cd",
              "value": "accounts_tmout"
            }
          ]
        },
        {
          "uuid": "057d79e6-2616-4f41-afdf-cbaa5c4fcdcc",
          "control-id": "ac-11",
          "props": [
            {
              "name": "Rule_Id",
              "ns": "https://oscal-compass/compliance-trestle/schemas/oscal/cd",
              "value": "accounts_tmout"
            }
          ]
        },
        {
          "uuid": "47a3295c-d421-490f-8191-3b7c9af763a1",
          "control-id": "ac-11.1",
          "props": [
            {
              "name": "Rule_Id",
              "ns": "https://oscal-compass/compliance-trestle/schemas/oscal/cd",
              "value": "accounts_tmout"
            }
          ]
        },
        {
          "uuid": "efe2bbdd-6472-4083-b657-8f9681f16411",
          "control-id": "ac-12",
          "props": [
            {
              "name": "Rule_Id",
              "ns": "https://oscal-compass/compliance-trestle/schemas/oscal/cd",
              "value": "accounts_tmout"
            }
          ]
        },
        {
          "uuid": "4fcf41c5-5ca6-45be-ad17-623be2f6dcb0",
          "control-id": "ac-6.2",
          "props": [
            {
              "name": "Rule_Id",
              "ns": "https://oscal-compass/compliance-trestle/schemas/oscal/cd",
              "value": "package_sudo_installed"
            },
            {
              "name": "Rule_Id",
              "ns": "https://oscal-compass/compliance-trestle/schemas/oscal/cd",
              "value": "sshd_disable_root_login"
            },
            {
              "name": "Rule_Id",
              "ns": "https://oscal-compass/compliance-trestle/schemas/oscal/cd",
              "value": "sudo_add_use_pty"
            },
            {
              "name": "Rule_Id",
              "ns": "https://oscal-compass/compliance-trestle/schemas/oscal/cd",
              "value": "sudo_remove_no_authenticate"
            },
            {
              "name": "Rule_Id",
              "ns": "https://oscal-compass/compliance-trestle/schemas/oscal/cd",
              "value": "sudo_require_authentication"
            },
            {
              "name": "Rule_Id",
              "ns": "https://oscal-compass/compliance-trestle/schemas/oscal/cd",
              "value": "sudo_require_reauthentication"
            }
          ]
        },
        {
          "uuid": "8f789cf7-a420-4409-b155-44c4b7d33084",
          "control-id": "ac-6.5",
          "props": [
            {
              "name": "Rule_Id",
              "ns": "https://oscal-compass/compliance-trestle/schemas/oscal/cd",
              "value": "package_sudo_installed"
            },
            {
              "name": "Rule_Id",
              "ns": "https://oscal-compass/compliance-trestle/schemas/oscal/cd",
              "value": "sshd_disable_root_login"
            },
            {
              "name": "Rule_Id",
              "ns": "https://oscal-compass/compliance-trestle/schemas/oscal/cd",
              "value": "sudo_add_use_pty"
            },
            {
              "name": "Rule_Id",
              "ns": "https://oscal-compass/compliance-trestle/schemas/oscal/cd",
              "value": "sudo_remove_no_authenticate"
            },
            {
              "name": "Rule_Id",
              "ns": "https://oscal-compass/compliance-trestle/schemas/oscal/cd",
              "value": "sudo_require_authentication"
            },
            {
              "name": "Rule_Id",
              "ns": "https://oscal-compass/compliance-trestle/schemas/oscal/cd",
              "value": "sudo_require_reauthentication"
            }
          ]
        },
        {
          "uuid": "9b131444-a1c3-49cc-b673-a0a444f81dea",
          "control-id": "ac-1",
          "props": [
            {
              "name": "Rule_Id",
              "ns": "https://oscal-compass/compliance-trestle/schemas/oscal/cd",
              "value": "accounts_passwords_pam_faillock_deny"
            },
            {
              "name": "Rule_Id",
              "ns": "https://oscal-compass/compliance-trestle/schemas/oscal/cd",
              "value": "accounts_passwords_pam_faillock_enabled"
            },
            {
              "name": "Rule_Id",
              "ns": "https://oscal-compass/compliance-trestle/schemas/oscal/cd",
              "value": "accounts_passwords_pam_faillock_root_unlock_time"
            },
            {
              "name": "Rule_Id",
              "ns": "https://oscal-compass/compliance-trestle/schemas/oscal/cd",
              "value": "accounts_passwords_pam_faillock_unlock_time"
            }
          ]
        },
        {
          "uuid": "f3f3dd09-8b0f-4d5e-915d-d9ada2904484",
          "control-id": "ac-2",
          "props": [
            {
              "name": "Rule_Id",
              "ns": "https://oscal-compass/compliance-trestle/schemas/oscal/cd",
              "value": "accounts_passwords_pam_faillock_deny"
            },
            {
              "name": "Rule_Id",
              "ns": "https://oscal-compass/compliance-trestle/schemas/oscal/cd",
              "value": "accounts_passwords_pam_faillock_enabled"
            },
            {
              "name": "Rule_Id",
              "ns": "https://oscal-compass/compliance-trestle/schemas/oscal/cd",
              "value": "accounts_passwords_pam_faillock_root_unlock_time"
            },
            {
              "name": "Rule_Id",
              "ns": "https://oscal-compass/compliance-trestle/schemas/oscal/cd",
              "value": "accounts_passwords_pam_faillock_unlock_time"
            }
          ]
        },
        {
          "uuid": "e1a3a754-fa76-4334-b5a5-20bdef4c8fdc",
          "control-id": "ac-2.1",
          "props": [
            {
              "name": "Rule_Id",
              "ns": "https://oscal-compass/compliance-trestle/schemas/oscal/cd",
              "value": "accounts_passwords_pam_faillock_deny"
            },
            {
              "name": "Rule_Id",
              "ns": "https://oscal-compass/compliance-trestle/schemas/oscal/cd",
              "value": "accounts_passwords_pam_faillock_enabled"
            },
            {
              "name": "Rule_Id",
              "ns": "https://oscal-compass/compliance-trestle/schemas/oscal/cd",
              "value": "accounts_passwords_pam_faillock_root_unlock_time"
            },
            {
              "name": "Rule_Id",
              "ns": "https://oscal-compass/compliance-trestle/schemas/oscal/cd",
              "value": "accounts_passwords_pam_faillock_unlock_time"
            }
          ]
        },
        {
          "uuid": "59345fd2-9308-4a40-92aa-41c006a2e71f",
          "control-id": "au-2",
          "props": [
            {
              "name": "Rule_Id",
              "ns": "https://oscal-compass/compliance-trestle/schemas/oscal/cd",
              "value": "sshd_set_loglevel_info"
            }
          ]
        },
        {
          "uuid": "ed593e98-9c5a-4096-8cf0-1b6812ccd70e",
          "control-id": "au-7",
          "props": [
            {
              "name": "Rule_Id",
              "ns": "https://oscal-compass/compliance-trestle/schemas/oscal/cd",
              "value": "sshd_set_loglevel_info"
            },
            {
              "name": "Rule_Id",
              "ns": "https://oscal-compass/compliance-trestle/schemas/oscal/cd",
              "value": "sshd_set_max_auth_tries"
            },
            {
              "name": "Rule_Id",
              "ns": "https://oscal-compass/compliance-trestle/schemas/oscal/cd",
              "value": "sudo_custom_logfile"
            }
          ]
        },
        {
          "uuid": "75e86e83-52d6-4b9e-a33b-e33327e6ee5e",
          "control-id": "au-12",
          "props": [
            {
              "name": "Rule_Id",
              "ns": "https://oscal-compass/compliance-trestle/schemas/oscal/cd",
              "value": "sshd_set_loglevel_info"
            },
            {
              "name": "Rule_Id",
              "ns": "https://oscal-compass/compliance-trestle/schemas/oscal/cd",
              "value": "sshd_set_max_auth_tries"
            },
            {
              "name": "Rule_Id",
              "ns": "https://oscal-compass/compliance-trestle/schemas/oscal/cd",
              "value": "sudo_custom_logfile"
            }
          ]
        },
        {
          "uuid": "d0cdb8cd-2180-4f06-9dfa-6b4de93659a1",
          "control-id": "au-3",
          "props": [
            {
              "name": "Rule_Id",
              "ns": "https://oscal-compass/compliance-trestle/schemas/oscal/cd",
              "value": "sshd_set_max_auth_tries"
            },
            {
              "name": "Rule_Id",
              "ns": "https://oscal-compass/compliance-trestle/schemas/oscal/cd",
              "value": "sudo_custom_logfile"
            }
          ]
        },
        {
          "uuid": "c87d8e24-2162-4b65-8041-4122df2b1cda",
          "control-id": "au-3.1",
          "props": [
            {
              "name": "Rule_Id",
              "ns": "https://oscal-compass/compliance-trestle/schemas/oscal/cd",
              "value": "sshd_set_max_auth_tries"
            },
            {
              "name": "Rule_Id",
              "ns": "https://oscal-compass/compliance-trestle/schemas/oscal/cd",
              "value": "sudo_custom_logfile"
            }
          ]
        },
        {
          "uuid": "018be2e2-bcbf-456e-8993-5737054c8ee7",
          "control-id": "ac-17.1",
          "props": [
            {
              "name": "Rule_Id",
              "ns": "https://oscal-compass/compliance-trestle/schemas/oscal/cd",
              "value": "sshd_logging_enabled"
            }
          ]
        },
        {
          "uuid": "c7d573f0-401d-41cd-b27d-50cc45d51513",
          "control-id": "ac-2.2",
          "props": [
            {
              "name": "Rule_Id",
              "ns": "https://oscal-compass/compliance-trestle/schemas/oscal/cd",
              "value": "account_temporary_expiration_configured"
            }
          ]
        },
        {
          "uuid": "8dc073f1-a088-451d-a7eb-6bef47131dc7",
          "control-id": "ac-2.3",
          "props": [
            {
              "name": "Rule_Id",
              "ns": "https://oscal-compass/compliance-trestle/schemas/oscal/cd",
              "value": "account_disable_inactive_accounts"
            }
          ]
        },
        {
          "uuid": "3c107e97-95c0-4c64-aec0-6f8953c1f455",
          "control-id": "ac-6.1",
          "props": [
            {
              "name": "Rule_Id",
              "ns": "https://oscal-compass/compliance-trestle/schemas/oscal/cd",
              "value": "sudo_security_function_authorization"
            }
          ]
        },
        {
          "uuid": "f75e0d7e-97ee-4025-9f14-ffece7d79b98",
          "control-id": "au-6.1",
          "props": [
            {
              "name": "Rule_Id",
              "ns": "https://oscal-compass/compliance-trestle/schemas/oscal/cd",
              "value": "log_analysis_tool_configured"
            }
          ]
        },
        {
          "uuid": "f760efd5-8e3d-4159-84c5-bdbac1c0e8b7",
          "control-id": "cm-3.2",
          "props": [
            {
              "name": "Rule_Id",
              "ns": "https://oscal-compass/compliance-trestle/schemas/oscal/cd",
              "value": "change_control_documentation_required"
            }
          ]
        },
        {
          "uuid": "ee6a73f1-b14d-48ab-abd6-1d33ce3e0f18",
          "control-id": "si-2.2",
          "props": [
            {
              "name": "Rule_Id",
              "ns": "https://oscal-compass/compliance-trestle/schemas/oscal/cd",
              "value": "package_update_automation_configured"
            }
          ]
        },
        {
          "uuid": "ee2cc1d4-44f1-43cd-9a31-a3f6f2afd23a",
          "control-id": "si-4.2",
          "props": [
            {
              "name": "Rule_Id",
              "ns": "https://oscal-compass/compliance-trestle/schemas/oscal/cd",
              "value": "intrusion_detection_tool_installed"
            }
          ]
        }
      ]
    }
  }
}