<?xml version="1.0" encoding="UTF-8"?>
<Benchmark xmlns="http://checklists.nist.gov/xccdf/1.2"
           xmlns:xsi="http://www.w3.org/2001/XMLSchema-instance"
           id="xccdf_org.ssgproject.content_benchmark_UBUNTU-24-04"
           resolved="true">
  
  <status date="2026-05-07">accepted</status>
  <title>Guide to the Secure Configuration of Ubuntu 24.04 LTS</title>
  <description>
    This guide presents a catalog of security-relevant configuration settings for Ubuntu
    24.04 LTS. It is a rendering of content structured in the eXtensible Configuration
    Checklist Description Format (XCCDF) in order to support security automation.
  </description>
  <version>1.0.0</version>
  
  <Profile id="xccdf_org.ssgproject.content_profile_fedramp_moderate">
    <title>FedRAMP Moderate Baseline for Ubuntu 24.04 LTS</title>
    <description>
      This profile contains configuration checks that align to the FedRAMP Moderate baseline.
    </description>
  </Profile>
  
  <TestResult id="xccdf_org.open-scap_testresult_xccdf_org.ssgproject.content_profile_fedramp_moderate"
              start-time="2026-05-07T08:16:56.232025"
              end-time="2026-05-07T08:29:56.232025"
              version="1.2"
              test-system="cpe:/a:open-scap:openscap:1.3.9">
    
    <benchmark href="/usr/share/xml/scap/ssg/content/ssg-ubuntu2404-ds.xml"
               id="xccdf_org.ssgproject.content_benchmark_UBUNTU-24-04"/>
    
    <title>OSCAP Scan Result - Tertiary web server running Ubuntu 24.04 LTS</title>
    
    <identity authenticated="true" privileged="true">root</identity>
    
    <profile idref="xccdf_org.ssgproject.content_profile_fedramp_moderate"/>
    
    <target>ubuntu-web-03.example.com</target>
    <target-address>192.168.1.106</target-address>
    <target-facts>
      <fact name="urn:xccdf:fact:asset:identifier:host_name" type="string">ubuntu-web-03.example.com</fact>
      <fact name="urn:xccdf:fact:asset:identifier:ipv4" type="string">192.168.1.106</fact>
      <fact name="urn:xccdf:fact:asset:identifier:os_name" type="string">Ubuntu</fact>
      <fact name="urn:xccdf:fact:asset:identifier:os_version" type="string">24.04 LTS</fact>
    </target-facts>
    
    <platform idref="cpe:/o:canonical:ubuntu_linux:24.04"/>
    
    <score system="urn:xccdf:scoring:default" maximum="100.000000">88.0</score>
    
    <rule-result idref="xccdf_org.ssgproject.content_rule_accounts_password_pam_unix_enabled"
                 time="2026-05-07T08:17:05.232025"
                 severity="medium"
                 weight="1.000000">
      <result>pass</result>
      <ident system="https://nvd.nist.gov/cce/index.cfm">CCE-86370-2</ident>
      <check system="http://oval.mitre.org/XMLSchema/oval-definitions-5">
        <check-content-ref name="oval:ssg:def:828" href="ssg-ubuntu2404-oval.xml"/>
      </check>
    </rule-result>
    
    <rule-result idref="xccdf_org.ssgproject.content_rule_accounts_root_gid_zero"
                 time="2026-05-07T08:17:11.232025"
                 severity="low"
                 weight="1.000000">
      <result>pass</result>
      <ident system="https://nvd.nist.gov/cce/index.cfm">CCE-84280-5</ident>
      <check system="http://oval.mitre.org/XMLSchema/oval-definitions-5">
        <check-content-ref name="oval:ssg:def:231" href="ssg-ubuntu2404-oval.xml"/>
      </check>
    </rule-result>
    
    <rule-result idref="xccdf_org.ssgproject.content_rule_accounts_umask_etc_bashrc"
                 time="2026-05-07T08:17:20.232025"
                 severity="low"
                 weight="1.000000">
      <result>pass</result>
      <ident system="https://nvd.nist.gov/cce/index.cfm">CCE-83978-5</ident>
      <check system="http://oval.mitre.org/XMLSchema/oval-definitions-5">
        <check-content-ref name="oval:ssg:def:582" href="ssg-ubuntu2404-oval.xml"/>
      </check>
    </rule-result>
    
    <rule-result idref="xccdf_org.ssgproject.content_rule_accounts_umask_etc_login_defs"
                 time="2026-05-07T08:17:27.232025"
                 severity="low"
                 weight="1.000000">
      <result>fail</result>
      <ident system="https://nvd.nist.gov/cce/index.cfm">CCE-88139-6</ident>
      <check system="http://oval.mitre.org/XMLSchema/oval-definitions-5">
        <check-content-ref name="oval:ssg:def:351" href="ssg-ubuntu2404-oval.xml"/>
      </check>
      <message severity="error">Check failed: accounts_umask_etc_login_defs</message>
    </rule-result>
    
    <rule-result idref="xccdf_org.ssgproject.content_rule_accounts_umask_etc_profile"
                 time="2026-05-07T08:17:33.232025"
                 severity="low"
                 weight="1.000000">
      <result>pass</result>
      <ident system="https://nvd.nist.gov/cce/index.cfm">CCE-83788-9</ident>
      <check system="http://oval.mitre.org/XMLSchema/oval-definitions-5">
        <check-content-ref name="oval:ssg:def:935" href="ssg-ubuntu2404-oval.xml"/>
      </check>
    </rule-result>
    
    <rule-result idref="xccdf_org.ssgproject.content_rule_accounts_umask_root"
                 time="2026-05-07T08:17:38.232025"
                 severity="medium"
                 weight="1.000000">
      <result>pass</result>
      <ident system="https://nvd.nist.gov/cce/index.cfm">CCE-84250-5</ident>
      <check system="http://oval.mitre.org/XMLSchema/oval-definitions-5">
        <check-content-ref name="oval:ssg:def:802" href="ssg-ubuntu2404-oval.xml"/>
      </check>
    </rule-result>
    
    <rule-result idref="xccdf_org.ssgproject.content_rule_ensure_pam_wheel_group_empty"
                 time="2026-05-07T08:17:50.232025"
                 severity="medium"
                 weight="1.000000">
      <result>pass</result>
      <ident system="https://nvd.nist.gov/cce/index.cfm">CCE-86369-1</ident>
      <check system="http://oval.mitre.org/XMLSchema/oval-definitions-5">
        <check-content-ref name="oval:ssg:def:609" href="ssg-ubuntu2404-oval.xml"/>
      </check>
    </rule-result>
    
    <rule-result idref="xccdf_org.ssgproject.content_rule_ensure_root_access_controlled"
                 time="2026-05-07T08:17:55.232025"
                 severity="medium"
                 weight="1.000000">
      <result>pass</result>
      <ident system="https://nvd.nist.gov/cce/index.cfm">CCE-87950-8</ident>
      <check system="http://oval.mitre.org/XMLSchema/oval-definitions-5">
        <check-content-ref name="oval:ssg:def:180" href="ssg-ubuntu2404-oval.xml"/>
      </check>
    </rule-result>
    
    <rule-result idref="xccdf_org.ssgproject.content_rule_file_groupowner_sshd_config"
                 time="2026-05-07T08:18:08.232025"
                 severity="low"
                 weight="1.000000">
      <result>pass</result>
      <ident system="https://nvd.nist.gov/cce/index.cfm">CCE-81588-8</ident>
      <check system="http://oval.mitre.org/XMLSchema/oval-definitions-5">
        <check-content-ref name="oval:ssg:def:550" href="ssg-ubuntu2404-oval.xml"/>
      </check>
    </rule-result>
    
    <rule-result idref="xccdf_org.ssgproject.content_rule_file_owner_sshd_config"
                 time="2026-05-07T08:18:20.232025"
                 severity="low"
                 weight="1.000000">
      <result>fail</result>
      <ident system="https://nvd.nist.gov/cce/index.cfm">CCE-80476-0</ident>
      <check system="http://oval.mitre.org/XMLSchema/oval-definitions-5">
        <check-content-ref name="oval:ssg:def:683" href="ssg-ubuntu2404-oval.xml"/>
      </check>
      <message severity="error">Check failed: file_owner_sshd_config</message>
    </rule-result>
    
    <rule-result idref="xccdf_org.ssgproject.content_rule_file_permissions_sshd_config"
                 time="2026-05-07T08:18:25.232025"
                 severity="high"
                 weight="1.000000">
      <result>fail</result>
      <ident system="https://nvd.nist.gov/cce/index.cfm">CCE-84659-1</ident>
      <check system="http://oval.mitre.org/XMLSchema/oval-definitions-5">
        <check-content-ref name="oval:ssg:def:774" href="ssg-ubuntu2404-oval.xml"/>
      </check>
      <message severity="error">Check failed: file_permissions_sshd_config</message>
    </rule-result>
    
    <rule-result idref="xccdf_org.ssgproject.content_rule_file_permissions_sshd_private_key"
                 time="2026-05-07T08:18:31.232025"
                 severity="high"
                 weight="1.000000">
      <result>pass</result>
      <ident system="https://nvd.nist.gov/cce/index.cfm">CCE-87054-1</ident>
      <check system="http://oval.mitre.org/XMLSchema/oval-definitions-5">
        <check-content-ref name="oval:ssg:def:948" href="ssg-ubuntu2404-oval.xml"/>
      </check>
    </rule-result>
    
    <rule-result idref="xccdf_org.ssgproject.content_rule_file_permissions_sshd_pub_key"
                 time="2026-05-07T08:18:44.232025"
                 severity="high"
                 weight="1.000000">
      <result>fail</result>
      <ident system="https://nvd.nist.gov/cce/index.cfm">CCE-88267-0</ident>
      <check system="http://oval.mitre.org/XMLSchema/oval-definitions-5">
        <check-content-ref name="oval:ssg:def:854" href="ssg-ubuntu2404-oval.xml"/>
      </check>
      <message severity="error">Check failed: file_permissions_sshd_pub_key</message>
    </rule-result>
    
    <rule-result idref="xccdf_org.ssgproject.content_rule_groups_no_zero_gid_except_root"
                 time="2026-05-07T08:18:53.232025"
                 severity="medium"
                 weight="1.000000">
      <result>pass</result>
      <ident system="https://nvd.nist.gov/cce/index.cfm">CCE-87721-4</ident>
      <check system="http://oval.mitre.org/XMLSchema/oval-definitions-5">
        <check-content-ref name="oval:ssg:def:117" href="ssg-ubuntu2404-oval.xml"/>
      </check>
    </rule-result>
    
    <rule-result idref="xccdf_org.ssgproject.content_rule_no_invalid_shell_accounts_unlocked"
                 time="2026-05-07T08:19:01.232025"
                 severity="medium"
                 weight="1.000000">
      <result>pass</result>
      <ident system="https://nvd.nist.gov/cce/index.cfm">CCE-83590-5</ident>
      <check system="http://oval.mitre.org/XMLSchema/oval-definitions-5">
        <check-content-ref name="oval:ssg:def:647" href="ssg-ubuntu2404-oval.xml"/>
      </check>
    </rule-result>
    
    <rule-result idref="xccdf_org.ssgproject.content_rule_no_shelllogin_for_systemaccounts"
                 time="2026-05-07T08:19:15.232025"
                 severity="medium"
                 weight="1.000000">
      <result>pass</result>
      <ident system="https://nvd.nist.gov/cce/index.cfm">CCE-83270-5</ident>
      <check system="http://oval.mitre.org/XMLSchema/oval-definitions-5">
        <check-content-ref name="oval:ssg:def:229" href="ssg-ubuntu2404-oval.xml"/>
      </check>
    </rule-result>
    
    <rule-result idref="xccdf_org.ssgproject.content_rule_sshd_limit_user_access"
                 time="2026-05-07T08:19:28.232025"
                 severity="high"
                 weight="1.000000">
      <result>pass</result>
      <ident system="https://nvd.nist.gov/cce/index.cfm">CCE-83901-3</ident>
      <check system="http://oval.mitre.org/XMLSchema/oval-definitions-5">
        <check-content-ref name="oval:ssg:def:273" href="ssg-ubuntu2404-oval.xml"/>
      </check>
    </rule-result>
    
    <rule-result idref="xccdf_org.ssgproject.content_rule_use_pam_wheel_group_for_su"
                 time="2026-05-07T08:19:35.232025"
                 severity="low"
                 weight="1.000000">
      <result>pass</result>
      <ident system="https://nvd.nist.gov/cce/index.cfm">CCE-89198-2</ident>
      <check system="http://oval.mitre.org/XMLSchema/oval-definitions-5">
        <check-content-ref name="oval:ssg:def:909" href="ssg-ubuntu2404-oval.xml"/>
      </check>
    </rule-result>
    
    <rule-result idref="xccdf_org.ssgproject.content_rule_sshd_use_strong_ciphers"
                 time="2026-05-07T08:19:48.232025"
                 severity="high"
                 weight="1.000000">
      <result>pass</result>
      <ident system="https://nvd.nist.gov/cce/index.cfm">CCE-84149-9</ident>
      <check system="http://oval.mitre.org/XMLSchema/oval-definitions-5">
        <check-content-ref name="oval:ssg:def:970" href="ssg-ubuntu2404-oval.xml"/>
      </check>
    </rule-result>
    
    <rule-result idref="xccdf_org.ssgproject.content_rule_sshd_use_strong_kex"
                 time="2026-05-07T08:19:57.232025"
                 severity="high"
                 weight="1.000000">
      <result>pass</result>
      <ident system="https://nvd.nist.gov/cce/index.cfm">CCE-83201-1</ident>
      <check system="http://oval.mitre.org/XMLSchema/oval-definitions-5">
        <check-content-ref name="oval:ssg:def:898" href="ssg-ubuntu2404-oval.xml"/>
      </check>
    </rule-result>
    
    <rule-result idref="xccdf_org.ssgproject.content_rule_sshd_use_strong_macs"
                 time="2026-05-07T08:20:07.232025"
                 severity="high"
                 weight="1.000000">
      <result>pass</result>
      <ident system="https://nvd.nist.gov/cce/index.cfm">CCE-84888-2</ident>
      <check system="http://oval.mitre.org/XMLSchema/oval-definitions-5">
        <check-content-ref name="oval:ssg:def:865" href="ssg-ubuntu2404-oval.xml"/>
      </check>
    </rule-result>
    
    <rule-result idref="xccdf_org.ssgproject.content_rule_accounts_password_pam_pwhistory_use_authtok"
                 time="2026-05-07T08:20:13.232025"
                 severity="low"
                 weight="1.000000">
      <result>pass</result>
      <ident system="https://nvd.nist.gov/cce/index.cfm">CCE-80930-3</ident>
      <check system="http://oval.mitre.org/XMLSchema/oval-definitions-5">
        <check-content-ref name="oval:ssg:def:775" href="ssg-ubuntu2404-oval.xml"/>
      </check>
    </rule-result>
    
    <rule-result idref="xccdf_org.ssgproject.content_rule_accounts_password_pam_unix_authtok"
                 time="2026-05-07T08:20:25.232025"
                 severity="medium"
                 weight="1.000000">
      <result>pass</result>
      <ident system="https://nvd.nist.gov/cce/index.cfm">CCE-89256-4</ident>
      <check system="http://oval.mitre.org/XMLSchema/oval-definitions-5">
        <check-content-ref name="oval:ssg:def:897" href="ssg-ubuntu2404-oval.xml"/>
      </check>
    </rule-result>
    
    <rule-result idref="xccdf_org.ssgproject.content_rule_set_password_hashing_algorithm_logindefs"
                 time="2026-05-07T08:20:35.232025"
                 severity="low"
                 weight="1.000000">
      <result>pass</result>
      <ident system="https://nvd.nist.gov/cce/index.cfm">CCE-83944-2</ident>
      <check system="http://oval.mitre.org/XMLSchema/oval-definitions-5">
        <check-content-ref name="oval:ssg:def:344" href="ssg-ubuntu2404-oval.xml"/>
      </check>
    </rule-result>
    
    <rule-result idref="xccdf_org.ssgproject.content_rule_set_password_hashing_algorithm_systemauth"
                 time="2026-05-07T08:20:49.232025"
                 severity="medium"
                 weight="1.000000">
      <result>pass</result>
      <ident system="https://nvd.nist.gov/cce/index.cfm">CCE-84980-8</ident>
      <check system="http://oval.mitre.org/XMLSchema/oval-definitions-5">
        <check-content-ref name="oval:ssg:def:973" href="ssg-ubuntu2404-oval.xml"/>
      </check>
    </rule-result>
    
    <rule-result idref="xccdf_org.ssgproject.content_rule_account_disable_post_pw_expiration"
                 time="2026-05-07T08:21:00.232025"
                 severity="high"
                 weight="1.000000">
      <result>pass</result>
      <ident system="https://nvd.nist.gov/cce/index.cfm">CCE-85356-5</ident>
      <check system="http://oval.mitre.org/XMLSchema/oval-definitions-5">
        <check-content-ref name="oval:ssg:def:556" href="ssg-ubuntu2404-oval.xml"/>
      </check>
    </rule-result>
    
    <rule-result idref="xccdf_org.ssgproject.content_rule_accounts_maximum_age_login_defs"
                 time="2026-05-07T08:21:14.232025"
                 severity="low"
                 weight="1.000000">
      <result>fail</result>
      <ident system="https://nvd.nist.gov/cce/index.cfm">CCE-84853-5</ident>
      <check system="http://oval.mitre.org/XMLSchema/oval-definitions-5">
        <check-content-ref name="oval:ssg:def:604" href="ssg-ubuntu2404-oval.xml"/>
      </check>
      <message severity="error">Check failed: accounts_maximum_age_login_defs</message>
    </rule-result>
    
    <rule-result idref="xccdf_org.ssgproject.content_rule_accounts_minimum_age_login_defs"
                 time="2026-05-07T08:21:19.232025"
                 severity="medium"
                 weight="1.000000">
      <result>pass</result>
      <ident system="https://nvd.nist.gov/cce/index.cfm">CCE-81760-0</ident>
      <check system="http://oval.mitre.org/XMLSchema/oval-definitions-5">
        <check-content-ref name="oval:ssg:def:789" href="ssg-ubuntu2404-oval.xml"/>
      </check>
    </rule-result>
    
    <rule-result idref="xccdf_org.ssgproject.content_rule_accounts_password_last_change_is_in_past"
                 time="2026-05-07T08:21:34.232025"
                 severity="high"
                 weight="1.000000">
      <result>pass</result>
      <ident system="https://nvd.nist.gov/cce/index.cfm">CCE-85036-2</ident>
      <check system="http://oval.mitre.org/XMLSchema/oval-definitions-5">
        <check-content-ref name="oval:ssg:def:762" href="ssg-ubuntu2404-oval.xml"/>
      </check>
    </rule-result>
    
    <rule-result idref="xccdf_org.ssgproject.content_rule_accounts_password_pam_dcredit"
                 time="2026-05-07T08:21:49.232025"
                 severity="high"
                 weight="1.000000">
      <result>pass</result>
      <ident system="https://nvd.nist.gov/cce/index.cfm">CCE-84092-3</ident>
      <check system="http://oval.mitre.org/XMLSchema/oval-definitions-5">
        <check-content-ref name="oval:ssg:def:196" href="ssg-ubuntu2404-oval.xml"/>
      </check>
    </rule-result>
    
    <rule-result idref="xccdf_org.ssgproject.content_rule_accounts_password_pam_dictcheck"
                 time="2026-05-07T08:21:59.232025"
                 severity="medium"
                 weight="1.000000">
      <result>pass</result>
      <ident system="https://nvd.nist.gov/cce/index.cfm">CCE-81485-7</ident>
      <check system="http://oval.mitre.org/XMLSchema/oval-definitions-5">
        <check-content-ref name="oval:ssg:def:411" href="ssg-ubuntu2404-oval.xml"/>
      </check>
    </rule-result>
    
    <rule-result idref="xccdf_org.ssgproject.content_rule_accounts_password_pam_difok"
                 time="2026-05-07T08:22:12.232025"
                 severity="low"
                 weight="1.000000">
      <result>pass</result>
      <ident system="https://nvd.nist.gov/cce/index.cfm">CCE-86987-0</ident>
      <check system="http://oval.mitre.org/XMLSchema/oval-definitions-5">
        <check-content-ref name="oval:ssg:def:606" href="ssg-ubuntu2404-oval.xml"/>
      </check>
    </rule-result>
    
    <rule-result idref="xccdf_org.ssgproject.content_rule_accounts_password_pam_enforce_root"
                 time="2026-05-07T08:22:27.232025"
                 severity="medium"
                 weight="1.000000">
      <result>pass</result>
      <ident system="https://nvd.nist.gov/cce/index.cfm">CCE-80785-5</ident>
      <check system="http://oval.mitre.org/XMLSchema/oval-definitions-5">
        <check-content-ref name="oval:ssg:def:436" href="ssg-ubuntu2404-oval.xml"/>
      </check>
    </rule-result>
    
    <rule-result idref="xccdf_org.ssgproject.content_rule_accounts_password_pam_enforcing"
                 time="2026-05-07T08:22:39.232025"
                 severity="medium"
                 weight="1.000000">
      <result>pass</result>
      <ident system="https://nvd.nist.gov/cce/index.cfm">CCE-80550-9</ident>
      <check system="http://oval.mitre.org/XMLSchema/oval-definitions-5">
        <check-content-ref name="oval:ssg:def:615" href="ssg-ubuntu2404-oval.xml"/>
      </check>
    </rule-result>
    
    <rule-result idref="xccdf_org.ssgproject.content_rule_accounts_password_pam_lcredit"
                 time="2026-05-07T08:22:51.232025"
                 severity="low"
                 weight="1.000000">
      <result>pass</result>
      <ident system="https://nvd.nist.gov/cce/index.cfm">CCE-87715-9</ident>
      <check system="http://oval.mitre.org/XMLSchema/oval-definitions-5">
        <check-content-ref name="oval:ssg:def:739" href="ssg-ubuntu2404-oval.xml"/>
      </check>
    </rule-result>
    
    <rule-result idref="xccdf_org.ssgproject.content_rule_accounts_password_pam_maxrepeat"
                 time="2026-05-07T08:23:00.232025"
                 severity="medium"
                 weight="1.000000">
      <result>pass</result>
      <ident system="https://nvd.nist.gov/cce/index.cfm">CCE-89997-7</ident>
      <check system="http://oval.mitre.org/XMLSchema/oval-definitions-5">
        <check-content-ref name="oval:ssg:def:788" href="ssg-ubuntu2404-oval.xml"/>
      </check>
    </rule-result>
    
    <rule-result idref="xccdf_org.ssgproject.content_rule_accounts_password_pam_maxsequence"
                 time="2026-05-07T08:23:14.232025"
                 severity="low"
                 weight="1.000000">
      <result>pass</result>
      <ident system="https://nvd.nist.gov/cce/index.cfm">CCE-85280-2</ident>
      <check system="http://oval.mitre.org/XMLSchema/oval-definitions-5">
        <check-content-ref name="oval:ssg:def:365" href="ssg-ubuntu2404-oval.xml"/>
      </check>
    </rule-result>
    
    <rule-result idref="xccdf_org.ssgproject.content_rule_accounts_password_pam_minclass"
                 time="2026-05-07T08:23:22.232025"
                 severity="high"
                 weight="1.000000">
      <result>pass</result>
      <ident system="https://nvd.nist.gov/cce/index.cfm">CCE-81943-3</ident>
      <check system="http://oval.mitre.org/XMLSchema/oval-definitions-5">
        <check-content-ref name="oval:ssg:def:926" href="ssg-ubuntu2404-oval.xml"/>
      </check>
    </rule-result>
    
    <rule-result idref="xccdf_org.ssgproject.content_rule_accounts_password_pam_minlen"
                 time="2026-05-07T08:23:37.232025"
                 severity="medium"
                 weight="1.000000">
      <result>pass</result>
      <ident system="https://nvd.nist.gov/cce/index.cfm">CCE-82912-2</ident>
      <check system="http://oval.mitre.org/XMLSchema/oval-definitions-5">
        <check-content-ref name="oval:ssg:def:686" href="ssg-ubuntu2404-oval.xml"/>
      </check>
    </rule-result>
    
    <rule-result idref="xccdf_org.ssgproject.content_rule_accounts_password_pam_ocredit"
                 time="2026-05-07T08:23:46.232025"
                 severity="low"
                 weight="1.000000">
      <result>pass</result>
      <ident system="https://nvd.nist.gov/cce/index.cfm">CCE-85579-7</ident>
      <check system="http://oval.mitre.org/XMLSchema/oval-definitions-5">
        <check-content-ref name="oval:ssg:def:442" href="ssg-ubuntu2404-oval.xml"/>
      </check>
    </rule-result>
    
    <rule-result idref="xccdf_org.ssgproject.content_rule_accounts_password_pam_pwhistory_enabled"
                 time="2026-05-07T08:23:52.232025"
                 severity="medium"
                 weight="1.000000">
      <result>pass</result>
      <ident system="https://nvd.nist.gov/cce/index.cfm">CCE-81629-8</ident>
      <check system="http://oval.mitre.org/XMLSchema/oval-definitions-5">
        <check-content-ref name="oval:ssg:def:115" href="ssg-ubuntu2404-oval.xml"/>
      </check>
    </rule-result>
    
    <rule-result idref="xccdf_org.ssgproject.content_rule_accounts_password_pam_pwhistory_enforce_root"
                 time="2026-05-07T08:24:07.232025"
                 severity="low"
                 weight="1.000000">
      <result>pass</result>
      <ident system="https://nvd.nist.gov/cce/index.cfm">CCE-86491-9</ident>
      <check system="http://oval.mitre.org/XMLSchema/oval-definitions-5">
        <check-content-ref name="oval:ssg:def:788" href="ssg-ubuntu2404-oval.xml"/>
      </check>
    </rule-result>
    
    <rule-result idref="xccdf_org.ssgproject.content_rule_accounts_password_pam_pwhistory_remember"
                 time="2026-05-07T08:24:18.232025"
                 severity="medium"
                 weight="1.000000">
      <result>pass</result>
      <ident system="https://nvd.nist.gov/cce/index.cfm">CCE-84170-1</ident>
      <check system="http://oval.mitre.org/XMLSchema/oval-definitions-5">
        <check-content-ref name="oval:ssg:def:635" href="ssg-ubuntu2404-oval.xml"/>
      </check>
    </rule-result>
    
    <rule-result idref="xccdf_org.ssgproject.content_rule_accounts_password_pam_pwquality_enabled"
                 time="2026-05-07T08:24:28.232025"
                 severity="medium"
                 weight="1.000000">
      <result>pass</result>
      <ident system="https://nvd.nist.gov/cce/index.cfm">CCE-83472-4</ident>
      <check system="http://oval.mitre.org/XMLSchema/oval-definitions-5">
        <check-content-ref name="oval:ssg:def:189" href="ssg-ubuntu2404-oval.xml"/>
      </check>
    </rule-result>
    
    <rule-result idref="xccdf_org.ssgproject.content_rule_accounts_password_pam_ucredit"
                 time="2026-05-07T08:24:37.232025"
                 severity="medium"
                 weight="1.000000">
      <result>pass</result>
      <ident system="https://nvd.nist.gov/cce/index.cfm">CCE-82069-5</ident>
      <check system="http://oval.mitre.org/XMLSchema/oval-definitions-5">
        <check-content-ref name="oval:ssg:def:141" href="ssg-ubuntu2404-oval.xml"/>
      </check>
    </rule-result>
    
    <rule-result idref="xccdf_org.ssgproject.content_rule_accounts_password_pam_unix_no_remember"
                 time="2026-05-07T08:24:49.232025"
                 severity="low"
                 weight="1.000000">
      <result>pass</result>
      <ident system="https://nvd.nist.gov/cce/index.cfm">CCE-80586-2</ident>
      <check system="http://oval.mitre.org/XMLSchema/oval-definitions-5">
        <check-content-ref name="oval:ssg:def:817" href="ssg-ubuntu2404-oval.xml"/>
      </check>
    </rule-result>
    
    <rule-result idref="xccdf_org.ssgproject.content_rule_accounts_password_set_max_life_existing"
                 time="2026-05-07T08:24:54.232025"
                 severity="low"
                 weight="1.000000">
      <result>pass</result>
      <ident system="https://nvd.nist.gov/cce/index.cfm">CCE-85358-7</ident>
      <check system="http://oval.mitre.org/XMLSchema/oval-definitions-5">
        <check-content-ref name="oval:ssg:def:650" href="ssg-ubuntu2404-oval.xml"/>
      </check>
    </rule-result>
    
    <rule-result idref="xccdf_org.ssgproject.content_rule_accounts_password_set_min_life_existing"
                 time="2026-05-07T08:25:00.232025"
                 severity="high"
                 weight="1.000000">
      <result>pass</result>
      <ident system="https://nvd.nist.gov/cce/index.cfm">CCE-84595-8</ident>
      <check system="http://oval.mitre.org/XMLSchema/oval-definitions-5">
        <check-content-ref name="oval:ssg:def:553" href="ssg-ubuntu2404-oval.xml"/>
      </check>
    </rule-result>
    
    <rule-result idref="xccdf_org.ssgproject.content_rule_no_empty_passwords_unix"
                 time="2026-05-07T08:25:10.232025"
                 severity="medium"
                 weight="1.000000">
      <result>fail</result>
      <ident system="https://nvd.nist.gov/cce/index.cfm">CCE-84771-6</ident>
      <check system="http://oval.mitre.org/XMLSchema/oval-definitions-5">
        <check-content-ref name="oval:ssg:def:174" href="ssg-ubuntu2404-oval.xml"/>
      </check>
      <message severity="error">Check failed: no_empty_passwords_unix</message>
    </rule-result>
    
    <rule-result idref="xccdf_org.ssgproject.content_rule_sshd_disable_empty_passwords"
                 time="2026-05-07T08:25:16.232025"
                 severity="high"
                 weight="1.000000">
      <result>pass</result>
      <ident system="https://nvd.nist.gov/cce/index.cfm">CCE-81736-6</ident>
      <check system="http://oval.mitre.org/XMLSchema/oval-definitions-5">
        <check-content-ref name="oval:ssg:def:997" href="ssg-ubuntu2404-oval.xml"/>
      </check>
    </rule-result>
    
    <rule-result idref="xccdf_org.ssgproject.content_rule_sshd_disable_gssapi_auth"
                 time="2026-05-07T08:25:22.232025"
                 severity="low"
                 weight="1.000000">
      <result>fail</result>
      <ident system="https://nvd.nist.gov/cce/index.cfm">CCE-83809-7</ident>
      <check system="http://oval.mitre.org/XMLSchema/oval-definitions-5">
        <check-content-ref name="oval:ssg:def:920" href="ssg-ubuntu2404-oval.xml"/>
      </check>
      <message severity="error">Check failed: sshd_disable_gssapi_auth</message>
    </rule-result>
    
    <rule-result idref="xccdf_org.ssgproject.content_rule_sshd_disable_rhosts"
                 time="2026-05-07T08:25:27.232025"
                 severity="low"
                 weight="1.000000">
      <result>pass</result>
      <ident system="https://nvd.nist.gov/cce/index.cfm">CCE-87996-7</ident>
      <check system="http://oval.mitre.org/XMLSchema/oval-definitions-5">
        <check-content-ref name="oval:ssg:def:296" href="ssg-ubuntu2404-oval.xml"/>
      </check>
    </rule-result>
    
    <rule-result idref="xccdf_org.ssgproject.content_rule_sshd_enable_pam"
                 time="2026-05-07T08:25:37.232025"
                 severity="high"
                 weight="1.000000">
      <result>pass</result>
      <ident system="https://nvd.nist.gov/cce/index.cfm">CCE-86259-9</ident>
      <check system="http://oval.mitre.org/XMLSchema/oval-definitions-5">
        <check-content-ref name="oval:ssg:def:818" href="ssg-ubuntu2404-oval.xml"/>
      </check>
    </rule-result>
    
    <rule-result idref="xccdf_org.ssgproject.content_rule_accounts_password_warn_age_login_defs"
                 time="2026-05-07T08:25:50.232025"
                 severity="high"
                 weight="1.000000">
      <result>pass</result>
      <ident system="https://nvd.nist.gov/cce/index.cfm">CCE-89884-9</ident>
      <check system="http://oval.mitre.org/XMLSchema/oval-definitions-5">
        <check-content-ref name="oval:ssg:def:334" href="ssg-ubuntu2404-oval.xml"/>
      </check>
    </rule-result>
    
    <rule-result idref="xccdf_org.ssgproject.content_rule_sshd_disable_forwarding"
                 time="2026-05-07T08:26:00.232025"
                 severity="low"
                 weight="1.000000">
      <result>pass</result>
      <ident system="https://nvd.nist.gov/cce/index.cfm">CCE-82348-3</ident>
      <check system="http://oval.mitre.org/XMLSchema/oval-definitions-5">
        <check-content-ref name="oval:ssg:def:128" href="ssg-ubuntu2404-oval.xml"/>
      </check>
    </rule-result>
    
    <rule-result idref="xccdf_org.ssgproject.content_rule_accounts_tmout"
                 time="2026-05-07T08:26:14.232025"
                 severity="medium"
                 weight="1.000000">
      <result>pass</result>
      <ident system="https://nvd.nist.gov/cce/index.cfm">CCE-81855-3</ident>
      <check system="http://oval.mitre.org/XMLSchema/oval-definitions-5">
        <check-content-ref name="oval:ssg:def:283" href="ssg-ubuntu2404-oval.xml"/>
      </check>
    </rule-result>
    
    <rule-result idref="xccdf_org.ssgproject.content_rule_package_sudo_installed"
                 time="2026-05-07T08:26:28.232025"
                 severity="low"
                 weight="1.000000">
      <result>pass</result>
      <ident system="https://nvd.nist.gov/cce/index.cfm">CCE-84243-4</ident>
      <check system="http://oval.mitre.org/XMLSchema/oval-definitions-5">
        <check-content-ref name="oval:ssg:def:384" href="ssg-ubuntu2404-oval.xml"/>
      </check>
    </rule-result>
    
    <rule-result idref="xccdf_org.ssgproject.content_rule_sshd_disable_root_login"
                 time="2026-05-07T08:26:40.232025"
                 severity="medium"
                 weight="1.000000">
      <result>fail</result>
      <ident system="https://nvd.nist.gov/cce/index.cfm">CCE-86322-8</ident>
      <check system="http://oval.mitre.org/XMLSchema/oval-definitions-5">
        <check-content-ref name="oval:ssg:def:967" href="ssg-ubuntu2404-oval.xml"/>
      </check>
      <message severity="error">Check failed: sshd_disable_root_login</message>
    </rule-result>
    
    <rule-result idref="xccdf_org.ssgproject.content_rule_sudo_add_use_pty"
                 time="2026-05-07T08:26:48.232025"
                 severity="low"
                 weight="1.000000">
      <result>pass</result>
      <ident system="https://nvd.nist.gov/cce/index.cfm">CCE-82429-3</ident>
      <check system="http://oval.mitre.org/XMLSchema/oval-definitions-5">
        <check-content-ref name="oval:ssg:def:491" href="ssg-ubuntu2404-oval.xml"/>
      </check>
    </rule-result>
    
    <rule-result idref="xccdf_org.ssgproject.content_rule_sudo_remove_no_authenticate"
                 time="2026-05-07T08:26:56.232025"
                 severity="low"
                 weight="1.000000">
      <result>pass</result>
      <ident system="https://nvd.nist.gov/cce/index.cfm">CCE-89521-3</ident>
      <check system="http://oval.mitre.org/XMLSchema/oval-definitions-5">
        <check-content-ref name="oval:ssg:def:367" href="ssg-ubuntu2404-oval.xml"/>
      </check>
    </rule-result>
    
    <rule-result idref="xccdf_org.ssgproject.content_rule_sudo_require_authentication"
                 time="2026-05-07T08:27:10.232025"
                 severity="high"
                 weight="1.000000">
      <result>pass</result>
      <ident system="https://nvd.nist.gov/cce/index.cfm">CCE-83322-4</ident>
      <check system="http://oval.mitre.org/XMLSchema/oval-definitions-5">
        <check-content-ref name="oval:ssg:def:515" href="ssg-ubuntu2404-oval.xml"/>
      </check>
    </rule-result>
    
    <rule-result idref="xccdf_org.ssgproject.content_rule_sudo_require_reauthentication"
                 time="2026-05-07T08:27:16.232025"
                 severity="low"
                 weight="1.000000">
      <result>pass</result>
      <ident system="https://nvd.nist.gov/cce/index.cfm">CCE-87587-0</ident>
      <check system="http://oval.mitre.org/XMLSchema/oval-definitions-5">
        <check-content-ref name="oval:ssg:def:502" href="ssg-ubuntu2404-oval.xml"/>
      </check>
    </rule-result>
    
    <rule-result idref="xccdf_org.ssgproject.content_rule_accounts_passwords_pam_faillock_deny"
                 time="2026-05-07T08:27:22.232025"
                 severity="medium"
                 weight="1.000000">
      <result>pass</result>
      <ident system="https://nvd.nist.gov/cce/index.cfm">CCE-80001-6</ident>
      <check system="http://oval.mitre.org/XMLSchema/oval-definitions-5">
        <check-content-ref name="oval:ssg:def:643" href="ssg-ubuntu2404-oval.xml"/>
      </check>
    </rule-result>
    
    <rule-result idref="xccdf_org.ssgproject.content_rule_accounts_passwords_pam_faillock_enabled"
                 time="2026-05-07T08:27:30.232025"
                 severity="high"
                 weight="1.000000">
      <result>pass</result>
      <ident system="https://nvd.nist.gov/cce/index.cfm">CCE-83493-8</ident>
      <check system="http://oval.mitre.org/XMLSchema/oval-definitions-5">
        <check-content-ref name="oval:ssg:def:672" href="ssg-ubuntu2404-oval.xml"/>
      </check>
    </rule-result>
    
    <rule-result idref="xccdf_org.ssgproject.content_rule_accounts_passwords_pam_faillock_root_unlock_time"
                 time="2026-05-07T08:27:42.232025"
                 severity="medium"
                 weight="1.000000">
      <result>pass</result>
      <ident system="https://nvd.nist.gov/cce/index.cfm">CCE-82842-4</ident>
      <check system="http://oval.mitre.org/XMLSchema/oval-definitions-5">
        <check-content-ref name="oval:ssg:def:546" href="ssg-ubuntu2404-oval.xml"/>
      </check>
    </rule-result>
    
    <rule-result idref="xccdf_org.ssgproject.content_rule_accounts_passwords_pam_faillock_unlock_time"
                 time="2026-05-07T08:27:47.232025"
                 severity="high"
                 weight="1.000000">
      <result>pass</result>
      <ident system="https://nvd.nist.gov/cce/index.cfm">CCE-83774-1</ident>
      <check system="http://oval.mitre.org/XMLSchema/oval-definitions-5">
        <check-content-ref name="oval:ssg:def:840" href="ssg-ubuntu2404-oval.xml"/>
      </check>
    </rule-result>
    
    <rule-result idref="xccdf_org.ssgproject.content_rule_sshd_set_loglevel_info"
                 time="2026-05-07T08:27:58.232025"
                 severity="low"
                 weight="1.000000">
      <result>fail</result>
      <ident system="https://nvd.nist.gov/cce/index.cfm">CCE-89198-8</ident>
      <check system="http://oval.mitre.org/XMLSchema/oval-definitions-5">
        <check-content-ref name="oval:ssg:def:645" href="ssg-ubuntu2404-oval.xml"/>
      </check>
      <message severity="error">Check failed: sshd_set_loglevel_info</message>
    </rule-result>
    
    <rule-result idref="xccdf_org.ssgproject.content_rule_sshd_set_max_auth_tries"
                 time="2026-05-07T08:28:07.232025"
                 severity="medium"
                 weight="1.000000">
      <result>pass</result>
      <ident system="https://nvd.nist.gov/cce/index.cfm">CCE-84369-6</ident>
      <check system="http://oval.mitre.org/XMLSchema/oval-definitions-5">
        <check-content-ref name="oval:ssg:def:743" href="ssg-ubuntu2404-oval.xml"/>
      </check>
    </rule-result>
    
    <rule-result idref="xccdf_org.ssgproject.content_rule_sudo_custom_logfile"
                 time="2026-05-07T08:28:15.232025"
                 severity="high"
                 weight="1.000000">
      <result>fail</result>
      <ident system="https://nvd.nist.gov/cce/index.cfm">CCE-82400-7</ident>
      <check system="http://oval.mitre.org/XMLSchema/oval-definitions-5">
        <check-content-ref name="oval:ssg:def:775" href="ssg-ubuntu2404-oval.xml"/>
      </check>
      <message severity="error">Check failed: sudo_custom_logfile</message>
    </rule-result>
    
    <rule-result idref="xccdf_org.ssgproject.content_rule_account_automated_provisioning_enabled"
                 time="2026-05-07T08:28:21.232025"
                 severity="medium"
                 weight="1.000000">
      <result>pass</result>
      <ident system="https://nvd.nist.gov/cce/index.cfm">CCE-84540-0</ident>
      <check system="http://oval.mitre.org/XMLSchema/oval-definitions-5">
        <check-content-ref name="oval:ssg:def:918" href="ssg-ubuntu2404-oval.xml"/>
      </check>
    </rule-result>
    
    <rule-result idref="xccdf_org.ssgproject.content_rule_account_temporary_expiration_configured"
                 time="2026-05-07T08:28:31.232025"
                 severity="low"
                 weight="1.000000">
      <result>pass</result>
      <ident system="https://nvd.nist.gov/cce/index.cfm">CCE-85382-0</ident>
      <check system="http://oval.mitre.org/XMLSchema/oval-definitions-5">
        <check-content-ref name="oval:ssg:def:711" href="ssg-ubuntu2404-oval.xml"/>
      </check>
    </rule-result>
    
    <rule-result idref="xccdf_org.ssgproject.content_rule_account_disable_inactive_accounts"
                 time="2026-05-07T08:28:39.232025"
                 severity="high"
                 weight="1.000000">
      <result>pass</result>
      <ident system="https://nvd.nist.gov/cce/index.cfm">CCE-84229-2</ident>
      <check system="http://oval.mitre.org/XMLSchema/oval-definitions-5">
        <check-content-ref name="oval:ssg:def:389" href="ssg-ubuntu2404-oval.xml"/>
      </check>
    </rule-result>
    
    <rule-result idref="xccdf_org.ssgproject.content_rule_sudo_security_function_authorization"
                 time="2026-05-07T08:28:44.232025"
                 severity="high"
                 weight="1.000000">
      <result>pass</result>
      <ident system="https://nvd.nist.gov/cce/index.cfm">CCE-87779-7</ident>
      <check system="http://oval.mitre.org/XMLSchema/oval-definitions-5">
        <check-content-ref name="oval:ssg:def:997" href="ssg-ubuntu2404-oval.xml"/>
      </check>
    </rule-result>
    
    <rule-result idref="xccdf_org.ssgproject.content_rule_service_nonprivileged_user_execution"
                 time="2026-05-07T08:28:56.232025"
                 severity="high"
                 weight="1.000000">
      <result>pass</result>
      <ident system="https://nvd.nist.gov/cce/index.cfm">CCE-89533-5</ident>
      <check system="http://oval.mitre.org/XMLSchema/oval-definitions-5">
        <check-content-ref name="oval:ssg:def:543" href="ssg-ubuntu2404-oval.xml"/>
      </check>
    </rule-result>
    
    <rule-result idref="xccdf_org.ssgproject.content_rule_screen_lock_timeout_configured"
                 time="2026-05-07T08:29:06.232025"
                 severity="high"
                 weight="1.000000">
      <result>pass</result>
      <ident system="https://nvd.nist.gov/cce/index.cfm">CCE-83595-8</ident>
      <check system="http://oval.mitre.org/XMLSchema/oval-definitions-5">
        <check-content-ref name="oval:ssg:def:667" href="ssg-ubuntu2404-oval.xml"/>
      </check>
    </rule-result>
    
    <rule-result idref="xccdf_org.ssgproject.content_rule_screen_lock_pattern_hiding_enabled"
                 time="2026-05-07T08:29:13.232025"
                 severity="medium"
                 weight="1.000000">
      <result>fail</result>
      <ident system="https://nvd.nist.gov/cce/index.cfm">CCE-84592-9</ident>
      <check system="http://oval.mitre.org/XMLSchema/oval-definitions-5">
        <check-content-ref name="oval:ssg:def:735" href="ssg-ubuntu2404-oval.xml"/>
      </check>
      <message severity="error">Check failed: screen_lock_pattern_hiding_enabled</message>
    </rule-result>
    
    <rule-result idref="xccdf_org.ssgproject.content_rule_sshd_logging_enabled"
                 time="2026-05-07T08:29:20.232025"
                 severity="low"
                 weight="1.000000">
      <result>pass</result>
      <ident system="https://nvd.nist.gov/cce/index.cfm">CCE-86710-1</ident>
      <check system="http://oval.mitre.org/XMLSchema/oval-definitions-5">
        <check-content-ref name="oval:ssg:def:168" href="ssg-ubuntu2404-oval.xml"/>
      </check>
    </rule-result>
    
    <rule-result idref="xccdf_org.ssgproject.content_rule_auditd_extended_information_enabled"
                 time="2026-05-07T08:29:30.232025"
                 severity="medium"
                 weight="1.000000">
      <result>pass</result>
      <ident system="https://nvd.nist.gov/cce/index.cfm">CCE-80825-8</ident>
      <check system="http://oval.mitre.org/XMLSchema/oval-definitions-5">
        <check-content-ref name="oval:ssg:def:483" href="ssg-ubuntu2404-oval.xml"/>
      </check>
    </rule-result>
    
    <rule-result idref="xccdf_org.ssgproject.content_rule_log_analysis_tool_configured"
                 time="2026-05-07T08:29:40.232025"
                 severity="high"
                 weight="1.000000">
      <result>pass</result>
      <ident system="https://nvd.nist.gov/cce/index.cfm">CCE-85003-0</ident>
      <check system="http://oval.mitre.org/XMLSchema/oval-definitions-5">
        <check-content-ref name="oval:ssg:def:192" href="ssg-ubuntu2404-oval.xml"/>
      </check>
    </rule-result>
    
    <rule-result idref="xccdf_org.ssgproject.content_rule_change_control_documentation_required"
                 time="2026-05-07T08:29:51.232025"
                 severity="medium"
                 weight="1.000000">
      <result>pass</result>
      <ident system="https://nvd.nist.gov/cce/index.cfm">CCE-82714-9</ident>
      <check system="http://oval.mitre.org/XMLSchema/oval-definitions-5">
        <check-content-ref name="oval:ssg:def:467" href="ssg-ubuntu2404-oval.xml"/>
      </check>
    </rule-result>
    
    <rule-result idref="xccdf_org.ssgproject.content_rule_service_periodic_review_enabled"
                 time="2026-05-07T08:30:03.232025"
                 severity="high"
                 weight="1.000000">
      <result>pass</result>
      <ident system="https://nvd.nist.gov/cce/index.cfm">CCE-87026-5</ident>
      <check system="http://oval.mitre.org/XMLSchema/oval-definitions-5">
        <check-content-ref name="oval:ssg:def:522" href="ssg-ubuntu2404-oval.xml"/>
      </check>
    </rule-result>
    
    <rule-result idref="xccdf_org.ssgproject.content_rule_package_update_automation_configured"
                 time="2026-05-07T08:30:11.232025"
                 severity="medium"
                 weight="1.000000">
      <result>fail</result>
      <ident system="https://nvd.nist.gov/cce/index.cfm">CCE-84848-2</ident>
      <check system="http://oval.mitre.org/XMLSchema/oval-definitions-5">
        <check-content-ref name="oval:ssg:def:244" href="ssg-ubuntu2404-oval.xml"/>
      </check>
      <message severity="error">Check failed: package_update_automation_configured</message>
    </rule-result>
    
    <rule-result idref="xccdf_org.ssgproject.content_rule_intrusion_detection_tool_installed"
                 time="2026-05-07T08:30:20.232025"
                 severity="high"
                 weight="1.000000">
      <result>fail</result>
      <ident system="https://nvd.nist.gov/cce/index.cfm">CCE-89477-1</ident>
      <check system="http://oval.mitre.org/XMLSchema/oval-definitions-5">
        <check-content-ref name="oval:ssg:def:321" href="ssg-ubuntu2404-oval.xml"/>
      </check>
      <message severity="error">Check failed: intrusion_detection_tool_installed</message>
    </rule-result>
    
    <rule-result idref="xccdf_org.ssgproject.content_rule_encrypted_traffic_inspection_configured"
                 time="2026-05-07T08:30:28.232025"
                 severity="high"
                 weight="1.000000">
      <result>fail</result>
      <ident system="https://nvd.nist.gov/cce/index.cfm">CCE-88209-0</ident>
      <check system="http://oval.mitre.org/XMLSchema/oval-definitions-5">
        <check-content-ref name="oval:ssg:def:191" href="ssg-ubuntu2404-oval.xml"/>
      </check>
      <message severity="error">Check failed: encrypted_traffic_inspection_configured</message>
    </rule-result>
    
    <rule-result idref="xccdf_org.ssgproject.content_rule_privileged_command_network_restriction"
                 time="2026-05-07T08:30:34.232025"
                 severity="low"
                 weight="1.000000">
      <result>pass</result>
      <ident system="https://nvd.nist.gov/cce/index.cfm">CCE-88777-8</ident>
      <check system="http://oval.mitre.org/XMLSchema/oval-definitions-5">
        <check-content-ref name="oval:ssg:def:297" href="ssg-ubuntu2404-oval.xml"/>
      </check>
    </rule-result>
    
    <rule-result idref="xccdf_org.ssgproject.content_rule_concurrent_session_limit_configured"
                 time="2026-05-07T08:30:44.232025"
                 severity="low"
                 weight="1.000000">
      <result>pass</result>
      <ident system="https://nvd.nist.gov/cce/index.cfm">CCE-80535-4</ident>
      <check system="http://oval.mitre.org/XMLSchema/oval-definitions-5">
        <check-content-ref name="oval:ssg:def:897" href="ssg-ubuntu2404-oval.xml"/>
      </check>
    </rule-result>
    
    <rule-result idref="xccdf_org.ssgproject.content_rule_auditd_storage_threshold_alert"
                 time="2026-05-07T08:30:59.232025"
                 severity="low"
                 weight="1.000000">
      <result>pass</result>
      <ident system="https://nvd.nist.gov/cce/index.cfm">CCE-83159-3</ident>
      <check system="http://oval.mitre.org/XMLSchema/oval-definitions-5">
        <check-content-ref name="oval:ssg:def:437" href="ssg-ubuntu2404-oval.xml"/>
      </check>
    </rule-result>
    
    <rule-result idref="xccdf_org.ssgproject.content_rule_auditd_realtime_alerts_enabled"
                 time="2026-05-07T08:31:13.232025"
                 severity="high"
                 weight="1.000000">
      <result>pass</result>
      <ident system="https://nvd.nist.gov/cce/index.cfm">CCE-87072-7</ident>
      <check system="http://oval.mitre.org/XMLSchema/oval-definitions-5">
        <check-content-ref name="oval:ssg:def:759" href="ssg-ubuntu2404-oval.xml"/>
      </check>
    </rule-result>
    
    <rule-result idref="xccdf_org.ssgproject.content_rule_centralized_logging_configured"
                 time="2026-05-07T08:31:26.232025"
                 severity="medium"
                 weight="1.000000">
      <result>pass</result>
      <ident system="https://nvd.nist.gov/cce/index.cfm">CCE-87098-7</ident>
      <check system="http://oval.mitre.org/XMLSchema/oval-definitions-5">
        <check-content-ref name="oval:ssg:def:729" href="ssg-ubuntu2404-oval.xml"/>
      </check>
    </rule-result>
    
    <rule-result idref="xccdf_org.ssgproject.content_rule_audit_logs_remote_storage"
                 time="2026-05-07T08:31:33.232025"
                 severity="low"
                 weight="1.000000">
      <result>pass</result>
      <ident system="https://nvd.nist.gov/cce/index.cfm">CCE-89133-5</ident>
      <check system="http://oval.mitre.org/XMLSchema/oval-definitions-5">
        <check-content-ref name="oval:ssg:def:662" href="ssg-ubuntu2404-oval.xml"/>
      </check>
    </rule-result>
    
    <rule-result idref="xccdf_org.ssgproject.content_rule_audit_logs_encrypted"
                 time="2026-05-07T08:31:41.232025"
                 severity="low"
                 weight="1.000000">
      <result>pass</result>
      <ident system="https://nvd.nist.gov/cce/index.cfm">CCE-86902-4</ident>
      <check system="http://oval.mitre.org/XMLSchema/oval-definitions-5">
        <check-content-ref name="oval:ssg:def:931" href="ssg-ubuntu2404-oval.xml"/>
      </check>
    </rule-result>
    
    <rule-result idref="xccdf_org.ssgproject.content_rule_critical_action_signing_enabled"
                 time="2026-05-07T08:31:49.232025"
                 severity="high"
                 weight="1.000000">
      <result>pass</result>
      <ident system="https://nvd.nist.gov/cce/index.cfm">CCE-88965-8</ident>
      <check system="http://oval.mitre.org/XMLSchema/oval-definitions-5">
        <check-content-ref name="oval:ssg:def:281" href="ssg-ubuntu2404-oval.xml"/>
      </check>
    </rule-result>
    
    <rule-result idref="xccdf_org.ssgproject.content_rule_time_synchronization_configured"
                 time="2026-05-07T08:31:55.232025"
                 severity="low"
                 weight="1.000000">
      <result>pass</result>
      <ident system="https://nvd.nist.gov/cce/index.cfm">CCE-83524-6</ident>
      <check system="http://oval.mitre.org/XMLSchema/oval-definitions-5">
        <check-content-ref name="oval:ssg:def:596" href="ssg-ubuntu2404-oval.xml"/>
      </check>
    </rule-result>
    
  </TestResult>
</Benchmark>
